{
  "fetched_at": "2025-05-30 13:45:27",
  "data": {
    "MMM": {
      "price": 148.73,
      "changePct": -0.6014898,
      "volume": 316225,
      "time": 1748612568
    },
    "AXP": {
      "price": 294.04,
      "changePct": -0.45365167,
      "volume": 144347,
      "time": 1748612575
    },
    "AMGN": {
      "price": 282.93,
      "changePct": -0.21514279,
      "volume": 107874,
      "time": 1748612579
    },
    "AMZN": {
      "price": 204.23,
      "changePct": -0.7146336,
      "volume": 2512032,
      "time": 1748612588
    },
    "AAPL": {
      "price": 198.52,
      "changePct": -0.71517515,
      "volume": 4173056,
      "time": 1748612589
    },
    "BA": {
      "price": 205.555,
      "changePct": -1.260928,
      "volume": 613163,
      "time": 1748612586
    },
    "CAT": {
      "price": 351.03,
      "changePct": -0.21593027,
      "volume": 125955,
      "time": 1748612589
    },
    "CVX": {
      "price": 137.043,
      "changePct": -0.62867403,
      "volume": 400108,
      "time": 1748612586
    },
    "CSCO": {
      "price": 62.725,
      "changePct": -0.51546514,
      "volume": 635042,
      "time": 1748612585
    },
    "KO": {
      "price": 72.155,
      "changePct": 0.93020135,
      "volume": 956522,
      "time": 1748612589
    },
    "DIS": {
      "price": 112.16,
      "changePct": 0.12498395,
      "volume": 374328,
      "time": 1748612583
    },
    "GS": {
      "price": 599.68,
      "changePct": -0.36220926,
      "volume": 95369,
      "time": 1748612567
    },
    "HD": {
      "price": 368.66,
      "changePct": 0.10046298,
      "volume": 121212,
      "time": 1748612586
    },
    "HON": {
      "price": 225.805,
      "changePct": 0.27309838,
      "volume": 118289,
      "time": 1748612589
    },
    "IBM": {
      "price": 258.43,
      "changePct": -0.10051017,
      "volume": 94227,
      "time": 1748612583
    },
    "JNJ": {
      "price": 154.435,
      "changePct": 0.5567103,
      "volume": 1408665,
      "time": 1748612591
    },
    "JPM": {
      "price": 263.575,
      "changePct": -0.30070844,
      "volume": 366815,
      "time": 1748612588
    },
    "MCD": {
      "price": 313.9428,
      "changePct": 0.6678717,
      "volume": 105758,
      "time": 1748612583
    },
    "MRK": {
      "price": 76.18,
      "changePct": -0.2879597,
      "volume": 734119,
      "time": 1748612589
    },
    "MSFT": {
      "price": 458.78,
      "changePct": 0.021800647,
      "volume": 913076,
      "time": 1748612593
    },
    "NKE": {
      "price": 60.6,
      "changePct": -1.3671877,
      "volume": 838382,
      "time": 1748612588
    },
    "NVDA": {
      "price": 137.16,
      "changePct": -1.4584372,
      "volume": 27048258,
      "time": 1748612592
    },
    "PG": {
      "price": 169.42,
      "changePct": 0.51020443,
      "volume": 542368,
      "time": 1748612590
    },
    "CRM": {
      "price": 265.58,
      "changePct": -0.5020331,
      "volume": 1024854,
      "time": 1748612590
    },
    "SHW": {
      "price": 355.42,
      "changePct": -0.092758,
      "volume": 31775,
      "time": 1748612581
    },
    "TRV": {
      "price": 275.03,
      "changePct": 0.22605202,
      "volume": 27002,
      "time": 1748612590
    },
    "UNH": {
      "price": 297.7,
      "changePct": -0.1576286,
      "volume": 815816,
      "time": 1748612592
    },
    "VZ": {
      "price": 43.6445,
      "changePct": 0.7258225,
      "volume": 683437,
      "time": 1748612591
    },
    "V": {
      "price": 363.725,
      "changePct": 0.36562148,
      "volume": 273339,
      "time": 1748612590
    },
    "WMT": {
      "price": 97.97,
      "changePct": 0.8959864,
      "volume": 915924,
      "time": 1748612595
    },
    "AOS": {
      "price": 64.23,
      "changePct": -0.7724393,
      "volume": 59649,
      "time": 1748612435
    },
    "ABT": {
      "price": 132.765,
      "changePct": -0.06398699,
      "volume": 128777,
      "time": 1748612585
    },
    "ABBV": {
      "price": 184.5,
      "changePct": -0.6033806,
      "volume": 173382,
      "time": 1748612588
    },
    "ACN": {
      "price": 316.74,
      "changePct": -0.31159183,
      "volume": 128328,
      "time": 1748612584
    },
    "ADBE": {
      "price": 413.23,
      "changePct": -0.031443384,
      "volume": 108638,
      "time": 1748612583
    },
    "AMD": {
      "price": 110.34,
      "changePct": -2.3799014,
      "volume": 3068695,
      "time": 1748612595
    },
    "AES": {
      "price": 10.0116,
      "changePct": -0.38196677,
      "volume": 604949,
      "time": 1748612596
    },
    "AFL": {
      "price": 103.3,
      "changePct": 0.4766127,
      "volume": 81122,
      "time": 1748612590
    },
    "A": {
      "price": 112.365,
      "changePct": -0.8077339,
      "volume": 109860,
      "time": 1748612597
    },
    "APD": {
      "price": 274.525,
      "changePct": 0.4958757,
      "volume": 81615,
      "time": 1748612597
    },
    "ABNB": {
      "price": 127.45,
      "changePct": -0.70894647,
      "volume": 509678,
      "time": 1748612592
    },
    "AKAM": {
      "price": 75.21,
      "changePct": -1.1561418,
      "volume": 64979,
      "time": 1748612597
    },
    "ALB": {
      "price": 55.54,
      "changePct": -3.3918955,
      "volume": 357840,
      "time": 1748612596
    },
    "ARE": {
      "price": 70.325,
      "changePct": -1.2982498,
      "volume": 62849,
      "time": 1748612582
    },
    "ALGN": {
      "price": 180.22,
      "changePct": -1.5460267,
      "volume": 60806,
      "time": 1748612551
    },
    "ALLE": {
      "price": 142.62,
      "changePct": -0.50925076,
      "volume": 7742,
      "time": 1748612516
    },
    "LNT": {
      "price": 62.01,
      "changePct": 0.25869015,
      "volume": 22456,
      "time": 1748612527
    },
    "ALL": {
      "price": 207.215,
      "changePct": 0.22006279,
      "volume": 26752,
      "time": 1748612599
    },
    "GOOGL": {
      "price": 170.39,
      "changePct": -0.8553481,
      "volume": 4425112,
      "time": 1748612601
    },
    "GOOG": {
      "price": 171.45,
      "changePct": -0.87303984,
      "volume": 1384783,
      "time": 1748612600
    },
    "MO": {
      "price": 60.15,
      "changePct": 1.1264324,
      "volume": 407736,
      "time": 1748612602
    },
    "AMCR": {
      "price": 9.085,
      "changePct": 0.05506734,
      "volume": 849326,
      "time": 1748612594
    },
    "AEE": {
      "price": 96.66,
      "changePct": 0.5095201,
      "volume": 33549,
      "time": 1748612599
    },
    "AEP": {
      "price": 102.955,
      "changePct": 0.4145158,
      "volume": 89089,
      "time": 1748612584
    },
    "AIG": {
      "price": 83.73,
      "changePct": 0.16749255,
      "volume": 84906,
      "time": 1748612594
    },
    "AMT": {
      "price": 214.31,
      "changePct": 0.28075,
      "volume": 79228,
      "time": 1748612588
    },
    "AWK": {
      "price": 142.448,
      "changePct": 0.6415182,
      "volume": 36114,
      "time": 1748612495
    },
    "AMP": {
      "price": 505.285,
      "changePct": -0.90896803,
      "volume": 10514,
      "time": 1748612136
    },
    "AME": {
      "price": 179.625,
      "changePct": -0.23050061,
      "volume": 30706,
      "time": 1748612571
    },
    "APH": {
      "price": 88.67,
      "changePct": -0.28116742,
      "volume": 375258,
      "time": 1748612603
    },
    "ADI": {
      "price": 213.45,
      "changePct": -1.06605,
      "volume": 172954,
      "time": 1748612588
    },
    "ANSS": {
      "price": 327.7725,
      "changePct": -0.29430518,
      "volume": 52289,
      "time": 1748612582
    },
    "AON": {
      "price": 368.405,
      "changePct": 0.40471637,
      "volume": 44082,
      "time": 1748612539
    },
    "APA": {
      "price": 17.0,
      "changePct": -1.9607852,
      "volume": 276560,
      "time": 1748612604
    },
    "APO": {
      "price": 129.61,
      "changePct": -1.5869373,
      "volume": 135725,
      "time": 1748612602
    },
    "AMAT": {
      "price": 155.715,
      "changePct": -2.3607972,
      "volume": 980841,
      "time": 1748612604
    },
    "APTV": {
      "price": 67.08,
      "changePct": -1.4839767,
      "volume": 76151,
      "time": 1748612604
    },
    "ACGL": {
      "price": 93.865,
      "changePct": -0.35562536,
      "volume": 44155,
      "time": 1748612603
    },
    "ADM": {
      "price": 47.825,
      "changePct": -1.1267277,
      "volume": 245371,
      "time": 1748612599
    },
    "ANET": {
      "price": 84.06,
      "changePct": -2.6743908,
      "volume": 1072902,
      "time": 1748612605
    },
    "AJG": {
      "price": 343.665,
      "changePct": 0.51623714,
      "volume": 24040,
      "time": 1748612547
    },
    "AIZ": {
      "price": 199.455,
      "changePct": -0.25255296,
      "volume": 14891,
      "time": 1748612596
    },
    "T": {
      "price": 27.631,
      "changePct": 0.91673255,
      "volume": 1607936,
      "time": 1748612603
    },
    "ATO": {
      "price": 154.92,
      "changePct": 0.3757949,
      "volume": 24780,
      "time": 1748612593
    },
    "ADSK": {
      "price": 295.695,
      "changePct": -0.43939146,
      "volume": 42312,
      "time": 1748612596
    },
    "ADP": {
      "price": 324.875,
      "changePct": 0.23293993,
      "volume": 39925,
      "time": 1748612603
    },
    "AZO": {
      "price": 3744.5,
      "changePct": 1.4847538,
      "volume": 9057,
      "time": 1748612607
    },
    "AVB": {
      "price": 204.855,
      "changePct": -0.5654832,
      "volume": 17584,
      "time": 1748612576
    },
    "AVY": {
      "price": 177.57,
      "changePct": -1.1577994,
      "volume": 27859,
      "time": 1748612458
    },
    "AXON": {
      "price": 736.29,
      "changePct": 0.82159144,
      "volume": 22435,
      "time": 1748612471
    },
    "BKR": {
      "price": 36.895,
      "changePct": -1.2441475,
      "volume": 167772,
      "time": 1748612606
    },
    "BALL": {
      "price": 53.4,
      "changePct": -0.28010777,
      "volume": 67652,
      "time": 1748612533
    },
    "BAC": {
      "price": 43.8712,
      "changePct": -0.83363724,
      "volume": 7105844,
      "time": 1748612607
    },
    "BAX": {
      "price": 30.24,
      "changePct": -0.94988835,
      "volume": 81215,
      "time": 1748612604
    },
    "BDX": {
      "price": 172.41,
      "changePct": -0.8111861,
      "volume": 65211,
      "time": 1748612599
    },
    "BRK.B": {
      "price": null,
      "changePct": null,
      "volume": null,
      "time": 1748612614
    },
    "BBY": {
      "price": 66.46,
      "changePct": 0.2110968,
      "volume": 317598,
      "time": 1748612607
    },
    "TECH": {
      "price": 48.07,
      "changePct": -0.5379725,
      "volume": 110757,
      "time": 1748612597
    },
    "BIIB": {
      "price": 131.43,
      "changePct": -0.9943558,
      "volume": 217732,
      "time": 1748612599
    },
    "BLK": {
      "price": 968.74,
      "changePct": -0.77638656,
      "volume": 19429,
      "time": 1748612609
    },
    "BX": {
      "price": 137.1,
      "changePct": -1.2816811,
      "volume": 130381,
      "time": 1748612596
    },
    "BK": {
      "price": 88.29,
      "changePct": -0.87571436,
      "volume": 149816,
      "time": 1748612611
    },
    "BKNG": {
      "price": 5507.71,
      "changePct": 0.10377973,
      "volume": 6220,
      "time": 1748612583
    },
    "BSX": {
      "price": 104.49,
      "changePct": -0.009571422,
      "volume": 202595,
      "time": 1748612611
    },
    "BMY": {
      "price": 47.716,
      "changePct": -0.28003946,
      "volume": 530802,
      "time": 1748612611
    },
    "AVGO": {
      "price": 238.85,
      "changePct": -1.289414,
      "volume": 1388842,
      "time": 1748612612
    },
    "BR": {
      "price": 240.34,
      "changePct": 0.25863305,
      "volume": 11485,
      "time": 1748612567
    },
    "BRO": {
      "price": 112.02,
      "changePct": 0.28648138,
      "volume": 23567,
      "time": 1748612570
    },
    "BF.B": {
      "price": null,
      "changePct": null,
      "volume": null,
      "time": 1561759658
    },
    "BLDR": {
      "price": 107.805,
      "changePct": -1.0327734,
      "volume": 73549,
      "time": 1748612581
    },
    "BG": {
      "price": 77.985,
      "changePct": -1.5589505,
      "volume": 48337,
      "time": 1748612585
    },
    "BXP": {
      "price": 68.235,
      "changePct": -0.89324313,
      "volume": 30232,
      "time": 1748612579
    },
    "CHRW": {
      "price": 95.845,
      "changePct": -0.26534575,
      "volume": 33886,
      "time": 1748612579
    },
    "CDNS": {
      "price": 280.98,
      "changePct": -1.2372545,
      "volume": 130738,
      "time": 1748612611
    },
    "CZR": {
      "price": 26.955,
      "changePct": -1.1551174,
      "volume": 174761,
      "time": 1748612615
    },
    "CPT": {
      "price": 116.23,
      "changePct": -0.58164424,
      "volume": 12756,
      "time": 1748612604
    },
    "CPB": {
      "price": 34.25,
      "changePct": 0.23412888,
      "volume": 139259,
      "time": 1748612611
    },
    "COF": {
      "price": 187.975,
      "changePct": -1.4599437,
      "volume": 133866,
      "time": 1748612612
    },
    "CAH": {
      "price": 153.63,
      "changePct": -0.2337818,
      "volume": 33907,
      "time": 1748612536
    },
    "KMX": {
      "price": 63.34,
      "changePct": 0.5396828,
      "volume": 93870,
      "time": 1748612602
    },
    "CCL": {
      "price": 23.07,
      "changePct": -0.3886017,
      "volume": 870913,
      "time": 1748612615
    },
    "CARR": {
      "price": 71.155,
      "changePct": -0.35709965,
      "volume": 237057,
      "time": 1748612609
    },
    "CBOE": {
      "price": 229.065,
      "changePct": 1.0833598,
      "volume": 26655,
      "time": 1748612539
    },
    "CBRE": {
      "price": 123.89,
      "changePct": -0.62565076,
      "volume": 31988,
      "time": 1748612610
    },
    "CDW": {
      "price": 180.92,
      "changePct": -0.7842105,
      "volume": 23391,
      "time": 1748612533
    },
    "COR": {
      "price": 291.175,
      "changePct": 0.16683936,
      "volume": 28873,
      "time": 1748612556
    },
    "CNC": {
      "price": 56.43,
      "changePct": -0.15923594,
      "volume": 85561,
      "time": 1748612608
    },
    "CNP": {
      "price": 37.13,
      "changePct": 0.05389506,
      "volume": 405182,
      "time": 1748612616
    },
    "CF": {
      "price": 89.875,
      "changePct": -0.26079303,
      "volume": 48388,
      "time": 1748612601
    },
    "CRL": {
      "price": 134.8577,
      "changePct": -2.0641253,
      "volume": 19283,
      "time": 1748612575
    },
    "SCHW": {
      "price": 86.975,
      "changePct": -0.8944891,
      "volume": 337753,
      "time": 1748612612
    },
    "CHTR": {
      "price": 394.19,
      "changePct": -0.40928605,
      "volume": 41985,
      "time": 1748612604
    },
    "CMG": {
      "price": 49.57,
      "changePct": -0.32180178,
      "volume": 554807,
      "time": 1748612618
    },
    "CB": {
      "price": 295.0,
      "changePct": 0.2889703,
      "volume": 49947,
      "time": 1748612611
    },
    "CHD": {
      "price": 98.615,
      "changePct": 0.4840009,
      "volume": 54134,
      "time": 1748612593
    },
    "CI": {
      "price": 313.375,
      "changePct": 0.42460856,
      "volume": 33162,
      "time": 1748612620
    },
    "CINF": {
      "price": 148.98,
      "changePct": -0.6601357,
      "volume": 23365,
      "time": 1748612616
    },
    "CTAS": {
      "price": 225.68,
      "changePct": 0.41378984,
      "volume": 32789,
      "time": 1748612613
    },
    "C": {
      "price": 74.69,
      "changePct": -1.112136,
      "volume": 555401,
      "time": 1748612612
    },
    "CFG": {
      "price": 39.865,
      "changePct": -0.9811144,
      "volume": 182942,
      "time": 1748612620
    },
    "CLX": {
      "price": 131.48,
      "changePct": 0.3740669,
      "volume": 83027,
      "time": 1748612605
    },
    "CME": {
      "price": 286.45,
      "changePct": 0.2028954,
      "volume": 49105,
      "time": 1748612605
    },
    "CMS": {
      "price": 69.721,
      "changePct": 0.24586286,
      "volume": 54675,
      "time": 1748612619
    },
    "CTSH": {
      "price": 80.1756,
      "changePct": -0.58819276,
      "volume": 112929,
      "time": 1748612623
    },
    "CL": {
      "price": 92.9707,
      "changePct": 0.72665226,
      "volume": 161772,
      "time": 1748612582
    },
    "CMCSA": {
      "price": 34.2546,
      "changePct": -0.07410054,
      "volume": 1050970,
      "time": 1748612619
    },
    "CAG": {
      "price": 22.66,
      "changePct": -0.044131637,
      "volume": 181579,
      "time": 1748612621
    },
    "COP": {
      "price": 85.19,
      "changePct": -0.4790793,
      "volume": 426227,
      "time": 1748612621
    },
    "ED": {
      "price": 104.2,
      "changePct": 0.7931515,
      "volume": 51576,
      "time": 1748612614
    },
    "STZ": {
      "price": 179.505,
      "changePct": -0.11407369,
      "volume": 67942,
      "time": 1748612622
    },
    "CEG": {
      "price": 304.7591,
      "changePct": 0.45788944,
      "volume": 107701,
      "time": 1748612605
    },
    "COO": {
      "price": 68.665,
      "changePct": -14.12581,
      "volume": 1226956,
      "time": 1748612624
    },
    "CPRT": {
      "price": 51.12,
      "changePct": -0.58365613,
      "volume": 552389,
      "time": 1748612624
    },
    "GLW": {
      "price": 49.31,
      "changePct": -0.7447643,
      "volume": 176642,
      "time": 1748612620
    },
    "CPAY": {
      "price": 325.13,
      "changePct": -1.3591762,
      "volume": 6317,
      "time": 1748612551
    },
    "CTVA": {
      "price": 69.97,
      "changePct": 0.3729768,
      "volume": 130136,
      "time": 1748612613
    },
    "CSGP": {
      "price": 72.71,
      "changePct": -1.8361018,
      "volume": 92224,
      "time": 1748612604
    },
    "COST": {
      "price": 1036.565,
      "changePct": 2.7583869,
      "volume": 546846,
      "time": 1748612624
    },
    "CTRA": {
      "price": 24.435,
      "changePct": -1.1928835,
      "volume": 277780,
      "time": 1748612617
    },
    "CRWD": {
      "price": 460.955,
      "changePct": 0.4675114,
      "volume": 275981,
      "time": 1748612623
    },
    "CCI": {
      "price": 100.355,
      "changePct": 0.004984943,
      "volume": 105946,
      "time": 1748612626
    },
    "CSX": {
      "price": 31.37,
      "changePct": 0.25567248,
      "volume": 466308,
      "time": 1748612624
    },
    "CMI": {
      "price": 323.61,
      "changePct": -0.38478115,
      "volume": 61608,
      "time": 1748612621
    },
    "CVS": {
      "price": 62.7568,
      "changePct": -0.036949944,
      "volume": 408974,
      "time": 1748612622
    },
    "DHR": {
      "price": 189.7,
      "changePct": -0.40426537,
      "volume": 143943,
      "time": 1748612619
    },
    "DRI": {
      "price": 214.54,
      "changePct": 0.38837048,
      "volume": 21209,
      "time": 1748612590
    },
    "DVA": {
      "price": 136.255,
      "changePct": -0.055011332,
      "volume": 17647,
      "time": 1748612612
    },
    "DAY": {
      "price": 57.92,
      "changePct": 0.381278,
      "volume": 100531,
      "time": 1748612615
    },
    "DECK": {
      "price": 103.9425,
      "changePct": -3.1019852,
      "volume": 210344,
      "time": 1748612628
    },
    "DE": {
      "price": 508.66,
      "changePct": 1.0348577,
      "volume": 166450,
      "time": 1748612564
    },
    "DELL": {
      "price": 113.96,
      "changePct": 0.2904488,
      "volume": 4355028,
      "time": 1748612629
    },
    "DAL": {
      "price": 48.355,
      "changePct": -0.29897,
      "volume": 398059,
      "time": 1748612625
    },
    "DVN": {
      "price": 30.585,
      "changePct": -1.6878364,
      "volume": 510818,
      "time": 1748612629
    },
    "DXCM": {
      "price": 85.955,
      "changePct": 1.290362,
      "volume": 126945,
      "time": 1748612628
    },
    "FANG": {
      "price": 135.73,
      "changePct": -1.5093257,
      "volume": 84836,
      "time": 1748612620
    },
    "DLR": {
      "price": 172.055,
      "changePct": -0.11900722,
      "volume": 106023,
      "time": 1748612614
    },
    "DFS": {
      "price": 200.05,
      "changePct": null,
      "volume": 31267850,
      "time": 1748612639
    },
    "DG": {
      "price": 97.87,
      "changePct": 0.8241507,
      "volume": 101430,
      "time": 1748612629
    },
    "DLTR": {
      "price": 91.0,
      "changePct": 0.46367648,
      "volume": 207240,
      "time": 1748612629
    },
    "D": {
      "price": 56.32,
      "changePct": 0.5355217,
      "volume": 167565,
      "time": 1748612604
    },
    "DPZ": {
      "price": 474.01,
      "changePct": -0.10747266,
      "volume": 11438,
      "time": 1748612565
    },
    "DASH": {
      "price": 204.6216,
      "changePct": 0.020332124,
      "volume": 127902,
      "time": 1748612615
    },
    "DOV": {
      "price": 178.63,
      "changePct": -0.29860097,
      "volume": 35609,
      "time": 1748612631
    },
    "DOW": {
      "price": 27.74,
      "changePct": -1.2459964,
      "volume": 1046852,
      "time": 1748612624
    },
    "DHI": {
      "price": 117.795,
      "changePct": -0.40162212,
      "volume": 107833,
      "time": 1748612625
    },
    "DTE": {
      "price": 136.87,
      "changePct": 0.44767404,
      "volume": 20309,
      "time": 1748612607
    },
    "DUK": {
      "price": 116.065,
      "changePct": 0.5327029,
      "volume": 114127,
      "time": 1748612608
    },
    "DD": {
      "price": 67.84,
      "changePct": -1.0646104,
      "volume": 94706,
      "time": 1748612617
    },
    "EMN": {
      "price": 80.125,
      "changePct": -1.6871166,
      "volume": 185041,
      "time": 1748612631
    },
    "ETN": {
      "price": 321.18,
      "changePct": -1.1175779,
      "volume": 109777,
      "time": 1748612596
    },
    "EBAY": {
      "price": 72.86,
      "changePct": 0.5661079,
      "volume": 157363,
      "time": 1748612633
    },
    "ECL": {
      "price": 264.455,
      "changePct": 0.062423103,
      "volume": 82929,
      "time": 1748612588
    },
    "EIX": {
      "price": 55.36,
      "changePct": -0.9305663,
      "volume": 113927,
      "time": 1748612625
    },
    "EW": {
      "price": 77.14,
      "changePct": -0.7593358,
      "volume": 108206,
      "time": 1748612632
    },
    "EA": {
      "price": 141.735,
      "changePct": -0.77358985,
      "volume": 361211,
      "time": 1748612629
    },
    "ELV": {
      "price": 382.38,
      "changePct": 0.48616564,
      "volume": 40327,
      "time": 1748612617
    },
    "EMR": {
      "price": 118.9793,
      "changePct": -0.7844369,
      "volume": 65584,
      "time": 1748612627
    },
    "ENPH": {
      "price": 38.86,
      "changePct": -0.96840227,
      "volume": 630168,
      "time": 1748612635
    },
    "ETR": {
      "price": 82.505,
      "changePct": 0.17605226,
      "volume": 63134,
      "time": 1748612631
    },
    "EOG": {
      "price": 108.245,
      "changePct": -1.4879819,
      "volume": 463302,
      "time": 1748612635
    },
    "EPAM": {
      "price": 171.98,
      "changePct": -1.0357941,
      "volume": 27528,
      "time": 1748612582
    },
    "EQT": {
      "price": 54.89,
      "changePct": -0.8668946,
      "volume": 266515,
      "time": 1748612634
    },
    "EFX": {
      "price": 261.115,
      "changePct": -0.7356016,
      "volume": 8513,
      "time": 1748612359
    },
    "EQIX": {
      "price": 884.135,
      "changePct": -0.37129498,
      "volume": 11993,
      "time": 1748612636
    },
    "EQR": {
      "price": 69.4096,
      "changePct": -0.8150958,
      "volume": 41216,
      "time": 1748612632
    },
    "ERIE": {
      "price": 355.67,
      "changePct": -0.103919536,
      "volume": 2090,
      "time": 1748611867
    },
    "ESS": {
      "price": 281.175,
      "changePct": -0.32083055,
      "volume": 11137,
      "time": 1748612432
    },
    "EL": {
      "price": 68.07,
      "changePct": -0.36592507,
      "volume": 312732,
      "time": 1748612637
    },
    "EG": {
      "price": 345.11,
      "changePct": -0.35802534,
      "volume": 12745,
      "time": 1748612554
    },
    "EVRG": {
      "price": 66.24,
      "changePct": 0.015086046,
      "volume": 92604,
      "time": 1748612621
    },
    "ES": {
      "price": 64.26,
      "changePct": 0.26526105,
      "volume": 154517,
      "time": 1748612632
    },
    "EXC": {
      "price": 43.8,
      "changePct": 0.22882946,
      "volume": 306541,
      "time": 1748612621
    },
    "EXE": {
      "price": 115.505,
      "changePct": -0.15128203,
      "volume": 77492,
      "time": 1748612636
    },
    "EXPE": {
      "price": 165.61,
      "changePct": -0.024143247,
      "volume": 61130,
      "time": 1748612620
    },
    "EXPD": {
      "price": 113.37,
      "changePct": 0.08829002,
      "volume": 54341,
      "time": 1748612640
    },
    "EXR": {
      "price": 150.1101,
      "changePct": -0.46408737,
      "volume": 17026,
      "time": 1748612616
    },
    "XOM": {
      "price": 102.075,
      "changePct": -0.598866,
      "volume": 749221,
      "time": 1748612640
    },
    "FFIV": {
      "price": 278.48,
      "changePct": -0.7519817,
      "volume": 12090,
      "time": 1748612627
    },
    "FDS": {
      "price": 462.485,
      "changePct": -0.42737225,
      "volume": 7468,
      "time": 1748612553
    },
    "FICO": {
      "price": 1708.37,
      "changePct": 1.3869433,
      "volume": 16869,
      "time": 1748612457
    },
    "FAST": {
      "price": 41.46,
      "changePct": 0.6310639,
      "volume": 164127,
      "time": 1748612628
    },
    "FRT": {
      "price": 95.43,
      "changePct": -0.56285274,
      "volume": 10551,
      "time": 1748612597
    },
    "FDX": {
      "price": 217.0,
      "changePct": -1.4800665,
      "volume": 79323,
      "time": 1748612639
    },
    "FIS": {
      "price": 78.0,
      "changePct": -0.34495547,
      "volume": 98916,
      "time": 1748612628
    },
    "FITB": {
      "price": 37.865,
      "changePct": -1.1873643,
      "volume": 145429,
      "time": 1748612632
    },
    "FSLR": {
      "price": 158.37,
      "changePct": 1.5517783,
      "volume": 217394,
      "time": 1748612642
    },
    "FE": {
      "price": 41.92,
      "changePct": 0.5275707,
      "volume": 102584,
      "time": 1748612621
    },
    "FI": {
      "price": 161.71,
      "changePct": 1.309366,
      "volume": 359970,
      "time": 1748612640
    },
    "F": {
      "price": 10.205,
      "changePct": -0.14682612,
      "volume": 3027023,
      "time": 1748612643
    },
    "FTNT": {
      "price": 101.71,
      "changePct": -0.32340437,
      "volume": 173644,
      "time": 1748612643
    },
    "FTV": {
      "price": 70.495,
      "changePct": -0.69727445,
      "volume": 105109,
      "time": 1748612627
    },
    "FOXA": {
      "price": 54.61,
      "changePct": -0.25570664,
      "volume": 107886,
      "time": 1748612636
    },
    "FOX": {
      "price": 50.02,
      "changePct": -0.2989789,
      "volume": 20827,
      "time": 1748612603
    },
    "BEN": {
      "price": 21.48,
      "changePct": -1.4678886,
      "volume": 209684,
      "time": 1748612640
    },
    "FCX": {
      "price": 38.36,
      "changePct": -1.7166235,
      "volume": 520180,
      "time": 1748612641
    },
    "GRMN": {
      "price": 201.24,
      "changePct": -0.7887946,
      "volume": 16744,
      "time": 1748612624
    },
    "IT": {
      "price": 434.89,
      "changePct": -0.15611565,
      "volume": 9799,
      "time": 1748612579
    },
    "GE": {
      "price": 244.315,
      "changePct": 0.06348246,
      "volume": 175781,
      "time": 1748612628
    },
    "GEHC": {
      "price": 70.0873,
      "changePct": -2.0169098,
      "volume": 101736,
      "time": 1748612626
    },
    "GEV": {
      "price": 471.22,
      "changePct": 0.01060929,
      "volume": 278799,
      "time": 1748612642
    },
    "GEN": {
      "price": 27.97,
      "changePct": -0.10714531,
      "volume": 97714,
      "time": 1748612630
    },
    "GNRC": {
      "price": 123.325,
      "changePct": -0.7684276,
      "volume": 12890,
      "time": 1748612636
    },
    "GD": {
      "price": 275.0,
      "changePct": -0.07267885,
      "volume": 23469,
      "time": 1748612616
    },
    "GIS": {
      "price": 54.265,
      "changePct": 0.50934935,
      "volume": 163451,
      "time": 1748612641
    },
    "GM": {
      "price": 48.94,
      "changePct": 0.7203097,
      "volume": 411370,
      "time": 1748612646
    },
    "GPC": {
      "price": 126.56,
      "changePct": 0.15034804,
      "volume": 24804,
      "time": 1748612643
    },
    "GILD": {
      "price": 109.96,
      "changePct": -1.0350118,
      "volume": 291356,
      "time": 1748612645
    },
    "GPN": {
      "price": 75.05,
      "changePct": -1.0547073,
      "volume": 78812,
      "time": 1748612640
    },
    "GL": {
      "price": 121.33,
      "changePct": 0.29759493,
      "volume": 28919,
      "time": 1748612563
    },
    "GDDY": {
      "price": 179.79,
      "changePct": -0.50359917,
      "volume": 17740,
      "time": 1748612569
    },
    "HAL": {
      "price": 19.66,
      "changePct": -2.091863,
      "volume": 789193,
      "time": 1748612646
    },
    "HIG": {
      "price": 130.04,
      "changePct": -0.16123356,
      "volume": 42714,
      "time": 1748612641
    },
    "HAS": {
      "price": 66.67,
      "changePct": -0.19461808,
      "volume": 47340,
      "time": 1748612615
    },
    "HCA": {
      "price": 375.96,
      "changePct": -0.71041924,
      "volume": 65130,
      "time": 1748612642
    },
    "DOC": {
      "price": 17.39,
      "changePct": -0.7420152,
      "volume": 150200,
      "time": 1748612645
    },
    "HSIC": {
      "price": 70.92,
      "changePct": -1.4702892,
      "volume": 55419,
      "time": 1748612648
    },
    "HSY": {
      "price": 161.255,
      "changePct": -0.04027038,
      "volume": 83488,
      "time": 1748612647
    },
    "HES": {
      "price": 132.9,
      "changePct": -0.53884244,
      "volume": 202782,
      "time": 1748612643
    },
    "HPE": {
      "price": 17.325,
      "changePct": -1.8413533,
      "volume": 576208,
      "time": 1748612631
    },
    "HLT": {
      "price": 248.0,
      "changePct": -0.1047267,
      "volume": 29248,
      "time": 1748612621
    },
    "HOLX": {
      "price": 62.045,
      "changePct": -1.3906548,
      "volume": 52716,
      "time": 1748612616
    },
    "HRL": {
      "price": 30.66,
      "changePct": 0.92166126,
      "volume": 138200,
      "time": 1748612617
    },
    "HST": {
      "price": 15.44,
      "changePct": -0.2583977,
      "volume": 393903,
      "time": 1748612640
    },
    "HWM": {
      "price": 168.45,
      "changePct": -0.9639117,
      "volume": 169852,
      "time": 1748612646
    },
    "HPQ": {
      "price": 24.6,
      "changePct": -1.4028071,
      "volume": 813902,
      "time": 1748612649
    },
    "HUBB": {
      "price": 394.245,
      "changePct": -0.34755573,
      "volume": 18052,
      "time": 1748612571
    },
    "HUM": {
      "price": 229.68,
      "changePct": -0.17385656,
      "volume": 37547,
      "time": 1748612632
    },
    "HBAN": {
      "price": 15.5052,
      "changePct": -1.3668636,
      "volume": 570871,
      "time": 1748612652
    },
    "HII": {
      "price": 221.44,
      "changePct": -0.40030557,
      "volume": 52305,
      "time": 1748612612
    },
    "IEX": {
      "price": 180.8,
      "changePct": -0.7356958,
      "volume": 23985,
      "time": 1748612402
    },
    "IDXX": {
      "price": 508.11,
      "changePct": -1.4431195,
      "volume": 29975,
      "time": 1748612606
    },
    "ITW": {
      "price": 244.93,
      "changePct": -0.32556182,
      "volume": 32115,
      "time": 1748612636
    },
    "INCY": {
      "price": 64.84,
      "changePct": -1.8170874,
      "volume": 62386,
      "time": 1748612651
    },
    "IR": {
      "price": 81.695,
      "changePct": -0.5538671,
      "volume": 105464,
      "time": 1748612653
    },
    "PODD": {
      "price": 322.345,
      "changePct": -0.4647228,
      "volume": 21752,
      "time": 1748612557
    },
    "INTC": {
      "price": 19.875,
      "changePct": -1.8518336,
      "volume": 9574882,
      "time": 1748612654
    },
    "ICE": {
      "price": 178.53,
      "changePct": 0.0,
      "volume": 56621,
      "time": 1748612654
    },
    "IFF": {
      "price": 75.72,
      "changePct": -0.4731869,
      "volume": 44263,
      "time": 1748612636
    },
    "IP": {
      "price": 47.405,
      "changePct": -1.1366048,
      "volume": 210683,
      "time": 1748612657
    },
    "IPG": {
      "price": 23.83,
      "changePct": -1.9744942,
      "volume": 252258,
      "time": 1748612657
    },
    "INTU": {
      "price": 756.835,
      "changePct": -0.050837107,
      "volume": 53704,
      "time": 1748612661
    },
    "ISRG": {
      "price": 552.25,
      "changePct": -0.6297796,
      "volume": 58577,
      "time": 1748612658
    },
    "IVZ": {
      "price": 14.515,
      "changePct": -1.593218,
      "volume": 118844,
      "time": 1748612658
    },
    "INVH": {
      "price": 33.49,
      "changePct": -0.02985465,
      "volume": 84482,
      "time": 1748612663
    },
    "IQV": {
      "price": 138.84,
      "changePct": -1.5458856,
      "volume": 91882,
      "time": 1748612629
    },
    "IRM": {
      "price": 97.58,
      "changePct": -0.22498462,
      "volume": 24702,
      "time": 1748612652
    },
    "JBHT": {
      "price": 138.58,
      "changePct": -1.0142844,
      "volume": 27394,
      "time": 1748612658
    },
    "JBL": {
      "price": 167.935,
      "changePct": -0.36488014,
      "volume": 41322,
      "time": 1748612664
    },
    "JKHY": {
      "price": 180.43,
      "changePct": 0.19435298,
      "volume": 7184,
      "time": 1748612513
    },
    "J": {
      "price": 125.85,
      "changePct": -0.13489777,
      "volume": 56433,
      "time": 1748612645
    },
    "JCI": {
      "price": 101.07,
      "changePct": -1.0475814,
      "volume": 151745,
      "time": 1748612660
    },
    "JNPR": {
      "price": 35.885,
      "changePct": -0.18081346,
      "volume": 32531,
      "time": 1748612636
    },
    "K": {
      "price": 82.46,
      "changePct": -0.048485957,
      "volume": 131196,
      "time": 1748612648
    },
    "KVUE": {
      "price": 23.765,
      "changePct": 0.7845609,
      "volume": 336338,
      "time": 1748612655
    },
    "KDP": {
      "price": 33.63,
      "changePct": 0.53811747,
      "volume": 386628,
      "time": 1748612669
    },
    "KEY": {
      "price": 15.67,
      "changePct": -1.7554842,
      "volume": 363966,
      "time": 1748612657
    },
    "KEYS": {
      "price": 157.2025,
      "changePct": -0.9186337,
      "volume": 25668,
      "time": 1748612627
    },
    "KMB": {
      "price": 143.98,
      "changePct": 0.097329944,
      "volume": 55064,
      "time": 1748612654
    },
    "KIM": {
      "price": 21.235,
      "changePct": -0.5386406,
      "volume": 94896,
      "time": 1748612666
    },
    "KMI": {
      "price": 27.965,
      "changePct": 0.16120394,
      "volume": 303152,
      "time": 1748612669
    },
    "KKR": {
      "price": 120.865,
      "changePct": -1.1975803,
      "volume": 122818,
      "time": 1748612654
    },
    "KLAC": {
      "price": 759.05,
      "changePct": -1.9277211,
      "volume": 36852,
      "time": 1748612663
    },
    "KHC": {
      "price": 26.6571,
      "changePct": 0.13935311,
      "volume": 737562,
      "time": 1748612670
    },
    "KR": {
      "price": 67.87,
      "changePct": 1.3741685,
      "volume": 876229,
      "time": 1748612669
    },
    "LHX": {
      "price": 243.795,
      "changePct": 0.15405472,
      "volume": 59940,
      "time": 1748612649
    },
    "LH": {
      "price": 246.0975,
      "changePct": -0.26443622,
      "volume": 19272,
      "time": 1748612658
    },
    "LRCX": {
      "price": 81.857,
      "changePct": -2.736456,
      "volume": 575998,
      "time": 1748612664
    },
    "LW": {
      "price": 54.75,
      "changePct": 0.9402624,
      "volume": 58381,
      "time": 1748612646
    },
    "LVS": {
      "price": 40.99,
      "changePct": -0.5579804,
      "volume": 602103,
      "time": 1748612664
    },
    "LDOS": {
      "price": 146.5,
      "changePct": -0.67782825,
      "volume": 40568,
      "time": 1748612670
    },
    "LEN": {
      "price": 105.32,
      "changePct": -0.70708025,
      "volume": 170336,
      "time": 1748612666
    },
    "LII": {
      "price": 564.695,
      "changePct": -0.8437213,
      "volume": 10081,
      "time": 1748612637
    },
    "LLY": {
      "price": 720.43,
      "changePct": -0.2961671,
      "volume": 228790,
      "time": 1748612673
    },
    "LIN": {
      "price": 465.705,
      "changePct": 0.35015514,
      "volume": 96618,
      "time": 1748612635
    },
    "LYV": {
      "price": 135.31,
      "changePct": -0.6169639,
      "volume": 767480,
      "time": 1748612671
    },
    "LKQ": {
      "price": 40.24,
      "changePct": -0.09928536,
      "volume": 36882,
      "time": 1748612665
    },
    "LMT": {
      "price": 473.575,
      "changePct": -0.02427542,
      "volume": 36679,
      "time": 1748612660
    },
    "L": {
      "price": 88.675,
      "changePct": -0.039403338,
      "volume": 12639,
      "time": 1748612666
    },
    "LOW": {
      "price": 224.465,
      "changePct": -0.20672937,
      "volume": 100218,
      "time": 1748612635
    },
    "LULU": {
      "price": 314.28,
      "changePct": -0.88618296,
      "volume": 139252,
      "time": 1748612672
    },
    "LYB": {
      "price": 56.59,
      "changePct": -1.7705268,
      "volume": 386784,
      "time": 1748612668
    },
    "MTB": {
      "price": 181.43,
      "changePct": -0.83625376,
      "volume": 18264,
      "time": 1748612528
    },
    "MPC": {
      "price": 159.59,
      "changePct": -0.20635432,
      "volume": 81751,
      "time": 1748612643
    },
    "MKTX": {
      "price": 215.26,
      "changePct": 0.5535432,
      "volume": 24273,
      "time": 1748612628
    },
    "MAR": {
      "price": 263.93,
      "changePct": 0.12139423,
      "volume": 33633,
      "time": 1748612651
    },
    "MMC": {
      "price": 231.97,
      "changePct": 0.20735052,
      "volume": 61285,
      "time": 1748612665
    },
    "MLM": {
      "price": 545.02,
      "changePct": -0.6308272,
      "volume": 9437,
      "time": 1748612410
    },
    "MAS": {
      "price": 62.37,
      "changePct": -1.7021306,
      "volume": 60266,
      "time": 1748612646
    },
    "MA": {
      "price": 579.195,
      "changePct": 0.2448991,
      "volume": 116635,
      "time": 1748612669
    },
    "MTCH": {
      "price": 29.61,
      "changePct": -1.888667,
      "volume": 113778,
      "time": 1748612648
    },
    "MKC": {
      "price": 72.525,
      "changePct": -0.034461096,
      "volume": 64905,
      "time": 1748612654
    },
    "MCK": {
      "price": 716.09,
      "changePct": 0.45311022,
      "volume": 28346,
      "time": 1748612662
    },
    "MDT": {
      "price": 82.1,
      "changePct": -0.3761742,
      "volume": 357864,
      "time": 1748612676
    },
    "META": {
      "price": 640.83,
      "changePct": -0.6542083,
      "volume": 866279,
      "time": 1748612678
    },
    "MET": {
      "price": 78.49,
      "changePct": -0.46918938,
      "volume": 105743,
      "time": 1748612653
    },
    "MTD": {
      "price": 1154.63,
      "changePct": -1.5811766,
      "volume": 8195,
      "time": 1748612544
    },
    "MGM": {
      "price": 31.46,
      "changePct": -0.85093117,
      "volume": 159542,
      "time": 1748612654
    },
    "MCHP": {
      "price": 57.28,
      "changePct": -1.4283288,
      "volume": 573314,
      "time": 1748612676
    },
    "MU": {
      "price": 94.125,
      "changePct": -2.7634327,
      "volume": 1289344,
      "time": 1748612678
    },
    "MAA": {
      "price": 154.78,
      "changePct": -0.62279373,
      "volume": 14631,
      "time": 1748612615
    },
    "MRNA": {
      "price": 26.01,
      "changePct": -3.4162645,
      "volume": 1259888,
      "time": 1748612678
    },
    "MHK": {
      "price": 100.11,
      "changePct": -1.9778681,
      "volume": 29121,
      "time": 1748612658
    },
    "MOH": {
      "price": 304.45,
      "changePct": 0.19087672,
      "volume": 10900,
      "time": 1748612606
    },
    "TAP": {
      "price": 53.645,
      "changePct": -0.10242142,
      "volume": 73004,
      "time": 1748612654
    },
    "MDLZ": {
      "price": 67.87,
      "changePct": 0.5928583,
      "volume": 252657,
      "time": 1748612669
    },
    "MPWR": {
      "price": 662.55,
      "changePct": -2.6692302,
      "volume": 25803,
      "time": 1748612674
    },
    "MNST": {
      "price": 64.025,
      "changePct": 0.6049688,
      "volume": 162380,
      "time": 1748612678
    },
    "MCO": {
      "price": 481.5,
      "changePct": -0.029070394,
      "volume": 36648,
      "time": 1748612529
    },
    "MS": {
      "price": 126.96,
      "changePct": -0.9363331,
      "volume": 141794,
      "time": 1748612679
    },
    "MOS": {
      "price": 35.875,
      "changePct": -0.09746546,
      "volume": 113770,
      "time": 1748612679
    },
    "MSI": {
      "price": 415.99,
      "changePct": -0.5831322,
      "volume": 24274,
      "time": 1748612616
    },
    "MSCI": {
      "price": 564.08,
      "changePct": -0.3392196,
      "volume": 7738,
      "time": 1748612441
    },
    "NDAQ": {
      "price": 83.08,
      "changePct": -0.35979304,
      "volume": 105373,
      "time": 1748612674
    },
    "NTAP": {
      "price": 98.67,
      "changePct": -0.54454786,
      "volume": 456008,
      "time": 1748612683
    },
    "NFLX": {
      "price": 1194.5801,
      "changePct": 0.8203579,
      "volume": 370308,
      "time": 1748612682
    },
    "NEM": {
      "price": 52.28,
      "changePct": -0.45697197,
      "volume": 657339,
      "time": 1748612681
    },
    "NWSA": {
      "price": 28.16,
      "changePct": -0.84506965,
      "volume": 50617,
      "time": 1748612665
    },
    "NWS": {
      "price": 32.775,
      "changePct": -0.3799392,
      "volume": 16430,
      "time": 1748612657
    },
    "NEE": {
      "price": 69.23,
      "changePct": 0.34788448,
      "volume": 296972,
      "time": 1748612678
    },
    "NI": {
      "price": 39.125,
      "changePct": 0.34623832,
      "volume": 76525,
      "time": 1748612677
    },
    "NDSN": {
      "price": 211.205,
      "changePct": 1.0695318,
      "volume": 23264,
      "time": 1748612654
    },
    "NSC": {
      "price": 248.945,
      "changePct": 1.0738953,
      "volume": 108184,
      "time": 1748612686
    },
    "NTRS": {
      "price": 106.08,
      "changePct": -1.155421,
      "volume": 71592,
      "time": 1748612672
    },
    "NOC": {
      "price": 479.76,
      "changePct": 0.07718037,
      "volume": 38303,
      "time": 1748612644
    },
    "NCLH": {
      "price": 17.525,
      "changePct": -0.4261407,
      "volume": 581209,
      "time": 1748612681
    },
    "NRG": {
      "price": 154.72,
      "changePct": 0.16184372,
      "volume": 108966,
      "time": 1748612686
    },
    "NUE": {
      "price": 106.53,
      "changePct": -2.2116213,
      "volume": 137749,
      "time": 1748612687
    },
    "NVR": {
      "price": 7067.06,
      "changePct": -0.4307801,
      "volume": 415,
      "time": 1748612151
    },
    "NXPI": {
      "price": 191.55,
      "changePct": -2.2155273,
      "volume": 66668,
      "time": 1748612682
    },
    "ORLY": {
      "price": 1372.5964,
      "changePct": 1.5188953,
      "volume": 13085,
      "time": 1748612622
    },
    "OXY": {
      "price": 40.96,
      "changePct": -1.2059817,
      "volume": 549893,
      "time": 1748612683
    },
    "ODFL": {
      "price": 160.595,
      "changePct": -0.8733988,
      "volume": 44648,
      "time": 1748612649
    },
    "OMC": {
      "price": 72.59,
      "changePct": -2.051011,
      "volume": 76620,
      "time": 1748612675
    },
    "ON": {
      "price": 42.03,
      "changePct": -2.1192358,
      "volume": 392073,
      "time": 1748612681
    },
    "OKE": {
      "price": 79.44,
      "changePct": -1.5369334,
      "volume": 217956,
      "time": 1748612673
    },
    "ORCL": {
      "price": 161.63,
      "changePct": -0.77961266,
      "volume": 266362,
      "time": 1748612689
    },
    "OTIS": {
      "price": 95.2072,
      "changePct": 0.049595837,
      "volume": 72648,
      "time": 1748612651
    },
    "PCAR": {
      "price": 93.92,
      "changePct": -0.39240932,
      "volume": 100711,
      "time": 1748612616
    },
    "PKG": {
      "price": 192.1,
      "changePct": -0.46631807,
      "volume": 14151,
      "time": 1748612638
    },
    "PLTR": {
      "price": 124.4289,
      "changePct": 1.724086,
      "volume": 10579962,
      "time": 1748612690
    },
    "PANW": {
      "price": 187.55,
      "changePct": 0.93133193,
      "volume": 285843,
      "time": 1748612689
    },
    "PARA": {
      "price": 12.1,
      "changePct": -0.6568138,
      "volume": 93344,
      "time": 1748612617
    },
    "PH": {
      "price": 663.37,
      "changePct": -0.578509,
      "volume": 14552,
      "time": 1748612637
    },
    "PAYX": {
      "price": 158.22,
      "changePct": 0.5081966,
      "volume": 43396,
      "time": 1748612671
    },
    "PAYC": {
      "price": 255.205,
      "changePct": -0.18577552,
      "volume": 25293,
      "time": 1748612654
    },
    "PYPL": {
      "price": 70.245,
      "changePct": -0.9657374,
      "volume": 772811,
      "time": 1748612691
    },
    "PNR": {
      "price": 98.79,
      "changePct": -0.7933329,
      "volume": 13777,
      "time": 1748612642
    },
    "PEP": {
      "price": 132.52,
      "changePct": 0.45482573,
      "volume": 472322,
      "time": 1748612690
    },
    "PFE": {
      "price": 23.295,
      "changePct": -0.66098374,
      "volume": 2221806,
      "time": 1748612690
    },
    "PCG": {
      "price": 17.04,
      "changePct": -0.17573978,
      "volume": 497973,
      "time": 1748612683
    },
    "PM": {
      "price": 179.74,
      "changePct": 1.0513355,
      "volume": 202934,
      "time": 1748612689
    },
    "PSX": {
      "price": 113.84,
      "changePct": -0.7324764,
      "volume": 89714,
      "time": 1748612683
    },
    "PNW": {
      "price": 91.03,
      "changePct": 0.20916118,
      "volume": 44310,
      "time": 1748612607
    },
    "PNC": {
      "price": 173.72,
      "changePct": -0.78812385,
      "volume": 45574,
      "time": 1748612688
    },
    "POOL": {
      "price": 299.29,
      "changePct": -0.4986868,
      "volume": 10849,
      "time": 1748612533
    },
    "PPG": {
      "price": 110.05,
      "changePct": -1.1319649,
      "volume": 43114,
      "time": 1748612636
    },
    "PPL": {
      "price": 34.46,
      "changePct": 0.11621417,
      "volume": 137136,
      "time": 1748612690
    },
    "PFG": {
      "price": 77.73,
      "changePct": -1.0439206,
      "volume": 50578,
      "time": 1748612663
    },
    "PGR": {
      "price": 278.66,
      "changePct": 0.4904508,
      "volume": 86336,
      "time": 1748612674
    },
    "PLD": {
      "price": 107.6,
      "changePct": -1.4922684,
      "volume": 289425,
      "time": 1748612693
    },
    "PRU": {
      "price": 103.495,
      "changePct": -0.8003441,
      "volume": 41704,
      "time": 1748612679
    },
    "PEG": {
      "price": 80.275,
      "changePct": 0.91137457,
      "volume": 137495,
      "time": 1748612693
    },
    "PTC": {
      "price": 167.385,
      "changePct": -0.32453892,
      "volume": 18911,
      "time": 1748612548
    },
    "PSA": {
      "price": 305.5,
      "changePct": -0.16996437,
      "volume": 17219,
      "time": 1748612691
    },
    "PHM": {
      "price": 98.03,
      "changePct": -0.5175584,
      "volume": 44860,
      "time": 1748612641
    },
    "PWR": {
      "price": 338.9884,
      "changePct": -0.22122416,
      "volume": 28529,
      "time": 1748612683
    },
    "QCOM": {
      "price": 146.1152,
      "changePct": -1.4997927,
      "volume": 303815,
      "time": 1748612694
    },
    "DGX": {
      "price": 171.4505,
      "changePct": -0.31947646,
      "volume": 21772,
      "time": 1748612667
    },
    "RL": {
      "price": 275.03,
      "changePct": -0.9721708,
      "volume": 27617,
      "time": 1748612615
    },
    "RJF": {
      "price": 146.15,
      "changePct": -1.0695188,
      "volume": 16069,
      "time": 1748612545
    },
    "RTX": {
      "price": 135.08,
      "changePct": 0.20771423,
      "volume": 135450,
      "time": 1748612678
    },
    "O": {
      "price": 56.5315,
      "changePct": 0.30429587,
      "volume": 418695,
      "time": 1748612698
    },
    "REG": {
      "price": 72.05,
      "changePct": -0.46967307,
      "volume": 26889,
      "time": 1748612661
    },
    "REGN": {
      "price": 501.905,
      "changePct": -17.093943,
      "volume": 903834,
      "time": 1748612698
    },
    "RF": {
      "price": 21.3,
      "changePct": -1.2517407,
      "volume": 316448,
      "time": 1748612699
    },
    "RSG": {
      "price": 255.795,
      "changePct": 0.5325404,
      "volume": 27879,
      "time": 1748612683
    },
    "RMD": {
      "price": 243.77,
      "changePct": -0.5507466,
      "volume": 14260,
      "time": 1748612609
    },
    "RVTY": {
      "price": 90.3253,
      "changePct": -1.7241867,
      "volume": 25671,
      "time": 1748612647
    },
    "ROK": {
      "price": 315.315,
      "changePct": 0.12225257,
      "volume": 54025,
      "time": 1748612651
    },
    "ROL": {
      "price": 57.39,
      "changePct": 0.82572246,
      "volume": 67439,
      "time": 1748612656
    },
    "ROP": {
      "price": 566.94,
      "changePct": 0.4731747,
      "volume": 31310,
      "time": 1748612686
    },
    "ROST": {
      "price": 139.16,
      "changePct": 0.16555892,
      "volume": 117733,
      "time": 1748612700
    },
    "RCL": {
      "price": 257.26,
      "changePct": 1.1083192,
      "volume": 164561,
      "time": 1748612699
    },
    "SPGI": {
      "price": 513.385,
      "changePct": -0.13907136,
      "volume": 320532,
      "time": 1748612691
    },
    "SBAC": {
      "price": 231.465,
      "changePct": 0.53204954,
      "volume": 23847,
      "time": 1748612666
    },
    "SLB": {
      "price": 33.02,
      "changePct": -1.9596195,
      "volume": 780741,
      "time": 1748612699
    },
    "STX": {
      "price": 117.405,
      "changePct": -0.62214375,
      "volume": 87174,
      "time": 1748612700
    },
    "SRE": {
      "price": 78.3,
      "changePct": 0.44901362,
      "volume": 101616,
      "time": 1748612674
    },
    "NOW": {
      "price": 1006.775,
      "changePct": -0.8328119,
      "volume": 49229,
      "time": 1748612697
    },
    "SPG": {
      "price": 162.06,
      "changePct": -0.7167789,
      "volume": 47601,
      "time": 1748612700
    },
    "SWKS": {
      "price": 67.85,
      "changePct": -2.3741028,
      "volume": 177921,
      "time": 1748612702
    },
    "SJM": {
      "price": 112.855,
      "changePct": 0.34231526,
      "volume": 24458,
      "time": 1748612654
    },
    "SW": {
      "price": 42.94,
      "changePct": -2.2090669,
      "volume": 250614,
      "time": 1748612702
    },
    "SNA": {
      "price": 321.81,
      "changePct": -0.17061298,
      "volume": 6266,
      "time": 1748612493
    },
    "SOLV": {
      "price": 71.875,
      "changePct": -1.0122586,
      "volume": 182962,
      "time": 1748612666
    },
    "SO": {
      "price": 89.19,
      "changePct": 0.4957774,
      "volume": 286792,
      "time": 1748612686
    },
    "LUV": {
      "price": 33.29,
      "changePct": -1.2459157,
      "volume": 436534,
      "time": 1748612700
    },
    "SWK": {
      "price": 65.13,
      "changePct": -2.1043162,
      "volume": 131554,
      "time": 1748612701
    },
    "SBUX": {
      "price": 83.645,
      "changePct": -0.48186365,
      "volume": 502296,
      "time": 1748612700
    },
    "STT": {
      "price": 95.96,
      "changePct": -1.112945,
      "volume": 60745,
      "time": 1748612694
    },
    "STLD": {
      "price": 122.49,
      "changePct": -2.1254523,
      "volume": 62474,
      "time": 1748612696
    },
    "STE": {
      "price": 242.86,
      "changePct": -0.8734695,
      "volume": 10433,
      "time": 1748612414
    },
    "SYK": {
      "price": 380.825,
      "changePct": -0.3988466,
      "volume": 35130,
      "time": 1748612682
    },
    "SMCI": {
      "price": 39.775,
      "changePct": -3.3414338,
      "volume": 4023013,
      "time": 1748612706
    },
    "SYF": {
      "price": 57.34,
      "changePct": -1.5622315,
      "volume": 48017,
      "time": 1748612701
    },
    "SNPS": {
      "price": 447.835,
      "changePct": -1.5725617,
      "volume": 127356,
      "time": 1748612701
    },
    "SYY": {
      "price": 72.66,
      "changePct": 0.81865406,
      "volume": 101120,
      "time": 1748612705
    },
    "TMUS": {
      "price": 240.55,
      "changePct": 0.8933835,
      "volume": 228225,
      "time": 1748612684
    },
    "TROW": {
      "price": 93.04,
      "changePct": -1.3466194,
      "volume": 44679,
      "time": 1748612700
    },
    "TTWO": {
      "price": 225.05,
      "changePct": -0.15084802,
      "volume": 104474,
      "time": 1748612677
    },
    "TPR": {
      "price": 77.88,
      "changePct": -0.71392804,
      "volume": 107356,
      "time": 1748612675
    },
    "TRGP": {
      "price": 156.41,
      "changePct": -1.3123868,
      "volume": 75340,
      "time": 1748612700
    },
    "TGT": {
      "price": 94.1198,
      "changePct": -0.7909118,
      "volume": 525941,
      "time": 1748612708
    },
    "TEL": {
      "price": 160.47,
      "changePct": -0.6685248,
      "volume": 28738,
      "time": 1748612702
    },
    "TDY": {
      "price": 493.03,
      "changePct": -0.8964843,
      "volume": 9503,
      "time": 1748612705
    },
    "TER": {
      "price": 78.56,
      "changePct": -2.9883993,
      "volume": 102285,
      "time": 1748612677
    },
    "TSLA": {
      "price": 356.44,
      "changePct": -0.55519634,
      "volume": 9573277,
      "time": 1748612710
    },
    "TXN": {
      "price": 182.42,
      "changePct": -1.3892682,
      "volume": 356343,
      "time": 1748612707
    },
    "TPL": {
      "price": 1187.2,
      "changePct": -0.928793,
      "volume": 2162,
      "time": 1748611801
    },
    "TXT": {
      "price": 73.71,
      "changePct": -0.39189327,
      "volume": 35462,
      "time": 1748612662
    },
    "TMO": {
      "price": 401.925,
      "changePct": -0.45206577,
      "volume": 133618,
      "time": 1748612711
    },
    "TJX": {
      "price": 127.22,
      "changePct": 0.11804637,
      "volume": 688644,
      "time": 1748612711
    },
    "TKO": {
      "price": 155.98,
      "changePct": -0.48488578,
      "volume": 13570,
      "time": 1748612596
    },
    "TSCO": {
      "price": 49.145,
      "changePct": 0.3573601,
      "volume": 163746,
      "time": 1748612709
    },
    "TT": {
      "price": 431.125,
      "changePct": -0.26949698,
      "volume": 118355,
      "time": 1748612705
    },
    "TDG": {
      "price": 1463.035,
      "changePct": 0.16122493,
      "volume": 7409,
      "time": 1748612246
    },
    "TRMB": {
      "price": 70.845,
      "changePct": -1.1345478,
      "volume": 45202,
      "time": 1748612710
    },
    "TFC": {
      "price": 39.2482,
      "changePct": -0.8884532,
      "volume": 347345,
      "time": 1748612711
    },
    "TYL": {
      "price": 573.01,
      "changePct": 0.23265062,
      "volume": 3366,
      "time": 1748612461
    },
    "TSN": {
      "price": 55.87,
      "changePct": 0.44947863,
      "volume": 101995,
      "time": 1748612689
    },
    "USB": {
      "price": 43.225,
      "changePct": -1.2225775,
      "volume": 230857,
      "time": 1748612710
    },
    "UBER": {
      "price": 82.99,
      "changePct": -1.55398,
      "volume": 2098129,
      "time": 1748612713
    },
    "UDR": {
      "price": 41.1,
      "changePct": -0.5321108,
      "volume": 36778,
      "time": 1748612700
    },
    "ULTA": {
      "price": 490.0,
      "changePct": 16.171553,
      "volume": 981264,
      "time": 1748612714
    },
    "UNP": {
      "price": 220.71,
      "changePct": -0.20798074,
      "volume": 113804,
      "time": 1748612675
    },
    "UAL": {
      "price": 77.675,
      "changePct": -1.1391073,
      "volume": 319434,
      "time": 1748612710
    },
    "UPS": {
      "price": 97.4,
      "changePct": -0.7135545,
      "volume": 243578,
      "time": 1748612714
    },
    "URI": {
      "price": 708.62,
      "changePct": -0.88953406,
      "volume": 68110,
      "time": 1748612593
    },
    "UHS": {
      "price": 190.455,
      "changePct": -0.3114373,
      "volume": 18251,
      "time": 1748612538
    },
    "VLO": {
      "price": 129.03,
      "changePct": -0.10065413,
      "volume": 130675,
      "time": 1748612715
    },
    "VTR": {
      "price": 64.27,
      "changePct": 0.18705378,
      "volume": 71252,
      "time": 1748612631
    },
    "VLTO": {
      "price": 101.145,
      "changePct": -0.09383762,
      "volume": 28225,
      "time": 1748612660
    },
    "VRSN": {
      "price": 268.64,
      "changePct": -0.014879421,
      "volume": 23188,
      "time": 1748612649
    },
    "VRSK": {
      "price": 315.33,
      "changePct": 0.32132196,
      "volume": 20103,
      "time": 1748612543
    },
    "VRTX": {
      "price": 443.5735,
      "changePct": -0.78653294,
      "volume": 55487,
      "time": 1748612683
    },
    "VTRS": {
      "price": 8.675,
      "changePct": -1.7553763,
      "volume": 679299,
      "time": 1748612713
    },
    "VICI": {
      "price": 31.64,
      "changePct": -0.094729036,
      "volume": 134830,
      "time": 1748612695
    },
    "VST": {
      "price": 159.04,
      "changePct": -0.4319805,
      "volume": 270684,
      "time": 1748612712
    },
    "VMC": {
      "price": 263.02,
      "changePct": -0.86314446,
      "volume": 23919,
      "time": 1748612677
    },
    "WRB": {
      "price": 74.09,
      "changePct": 0.17576663,
      "volume": 30727,
      "time": 1748612645
    },
    "GWW": {
      "price": 1091.4299,
      "changePct": 0.52406114,
      "volume": 2988,
      "time": 1748612489
    },
    "WAB": {
      "price": 200.96,
      "changePct": -0.24323168,
      "volume": 16723,
      "time": 1748612714
    },
    "WBA": {
      "price": 11.209,
      "changePct": -0.23141988,
      "volume": 443401,
      "time": 1748612702
    },
    "WBD": {
      "price": 9.91,
      "changePct": -1.2948219,
      "volume": 1228241,
      "time": 1748612715
    },
    "WM": {
      "price": 238.9,
      "changePct": 0.47947484,
      "volume": 62148,
      "time": 1748612710
    },
    "WAT": {
      "price": 349.19,
      "changePct": -1.7196695,
      "volume": 20113,
      "time": 1748612671
    },
    "WEC": {
      "price": 106.86,
      "changePct": 0.7923071,
      "volume": 61236,
      "time": 1748612675
    },
    "WFC": {
      "price": 73.845,
      "changePct": -0.89249885,
      "volume": 453236,
      "time": 1748612706
    },
    "WELL": {
      "price": 153.8,
      "changePct": 0.4767163,
      "volume": 162101,
      "time": 1748612716
    },
    "WST": {
      "price": 209.61,
      "changePct": -0.40388012,
      "volume": 13497,
      "time": 1748612648
    },
    "WDC": {
      "price": 52.01,
      "changePct": -1.0279857,
      "volume": 293964,
      "time": 1748612719
    },
    "WY": {
      "price": 25.81,
      "changePct": -0.07743112,
      "volume": 174407,
      "time": 1748612692
    },
    "WSM": {
      "price": 163.48,
      "changePct": -0.626101,
      "volume": 73486,
      "time": 1748612710
    },
    "WMB": {
      "price": 60.37,
      "changePct": 0.1659175,
      "volume": 264300,
      "time": 1748612721
    },
    "WTW": {
      "price": 315.1729,
      "changePct": -0.033965424,
      "volume": 13740,
      "time": 1748612617
    },
    "WDAY": {
      "price": 241.97,
      "changePct": 0.08686578,
      "volume": 111192,
      "time": 1748612716
    },
    "WYNN": {
      "price": 89.96,
      "changePct": -0.84867656,
      "volume": 108014,
      "time": 1748612718
    },
    "XEL": {
      "price": 69.75,
      "changePct": 0.40304992,
      "volume": 88617,
      "time": 1748612718
    },
    "XYL": {
      "price": 126.38,
      "changePct": 0.57296956,
      "volume": 82659,
      "time": 1748612706
    },
    "YUM": {
      "price": 144.215,
      "changePct": 0.121496156,
      "volume": 52595,
      "time": 1748612721
    },
    "ZBRA": {
      "price": 285.9075,
      "changePct": -2.2521732,
      "volume": 22125,
      "time": 1748612715
    },
    "ZBH": {
      "price": 92.34,
      "changePct": -1.0713521,
      "volume": 54580,
      "time": 1748612721
    },
    "ZTS": {
      "price": 166.61,
      "changePct": -0.31715563,
      "volume": 77178,
      "time": 1748612711
    },
    "APP": {
      "price": 382.2,
      "changePct": -0.5283291,
      "volume": 354246,
      "time": 1748612721
    },
    "ARM": {
      "price": 125.46,
      "changePct": -2.0608952,
      "volume": 496848,
      "time": 1748612722
    },
    "ASML": {
      "price": 740.65,
      "changePct": -0.85869074,
      "volume": 123998,
      "time": 1748612712
    },
    "AZN": {
      "price": 70.83,
      "changePct": -0.05644266,
      "volume": 466280,
      "time": 1748612718
    },
    "CCEP": {
      "price": 92.015,
      "changePct": 1.5057892,
      "volume": 119193,
      "time": 1748612722
    },
    "DDOG": {
      "price": 115.27,
      "changePct": -1.4786353,
      "volume": 167597,
      "time": 1748612718
    },
    "GFS": {
      "price": 36.0,
      "changePct": -2.465456,
      "volume": 78422,
      "time": 1748612667
    },
    "MDB": {
      "price": 185.04,
      "changePct": -2.2813728,
      "volume": 117425,
      "time": 1748612700
    },
    "MELI": {
      "price": 2540.17,
      "changePct": -0.20899977,
      "volume": 12600,
      "time": 1748612442
    },
    "MRVL": {
      "price": 58.92,
      "changePct": -7.5474677,
      "volume": 7944927,
      "time": 1748612726
    },
    "MSTR": {
      "price": 367.374,
      "changePct": -0.8785074,
      "volume": 719840,
      "time": 1748612725
    },
    "PDD": {
      "price": 95.4499,
      "changePct": -2.8895137,
      "volume": 3175297,
      "time": 1748612723
    },
    "TEAM": {
      "price": 202.23,
      "changePct": -0.8336179,
      "volume": 117342,
      "time": 1748612722
    },
    "TTD": {
      "price": 73.56,
      "changePct": -1.7628201,
      "volume": 264040,
      "time": 1748612726
    },
    "ZS": {
      "price": 269.3792,
      "changePct": 7.275382,
      "volume": 1263708,
      "time": 1748612719
    }
  }
}