{
  "fetched_at": "2025-09-25 17:43:21",
  "data": {
    "MMM": {
      "price": 152.19,
      "changePct": -1.5588639,
      "volume": 941418,
      "time": 1758822057
    },
    "AXP": {
      "price": 338.915,
      "changePct": -0.4596459,
      "volume": 970173,
      "time": 1758822042
    },
    "AMGN": {
      "price": 272.05,
      "changePct": -2.5678725,
      "volume": 1011849,
      "time": 1758822052
    },
    "AMZN": {
      "price": 218.46,
      "changePct": -0.794696,
      "volume": 27003061,
      "time": 1758822084
    },
    "AAPL": {
      "price": 253.3204,
      "changePct": 0.40046233,
      "volume": 24273373,
      "time": 1758822084
    },
    "BA": {
      "price": 213.9408,
      "changePct": -0.5389169,
      "volume": 3952786,
      "time": 1758822083
    },
    "CAT": {
      "price": 463.46,
      "changePct": -1.3474141,
      "volume": 1415572,
      "time": 1758822082
    },
    "CVX": {
      "price": 160.55,
      "changePct": 0.86066747,
      "volume": 2393611,
      "time": 1758822083
    },
    "CSCO": {
      "price": 67.6749,
      "changePct": 0.52721685,
      "volume": 11953523,
      "time": 1758822086
    },
    "KO": {
      "price": 66.1053,
      "changePct": -0.51873,
      "volume": 6888577,
      "time": 1758822087
    },
    "DIS": {
      "price": 112.79,
      "changePct": -0.56422406,
      "volume": 2924091,
      "time": 1758822082
    },
    "GS": {
      "price": 790.54,
      "changePct": -0.23857796,
      "volume": 829508,
      "time": 1758822086
    },
    "HD": {
      "price": 408.5901,
      "changePct": -0.2879423,
      "volume": 1130310,
      "time": 1758822019
    },
    "HON": {
      "price": 207.67,
      "changePct": -0.44583312,
      "volume": 1791928,
      "time": 1758822082
    },
    "IBM": {
      "price": 280.49,
      "changePct": 4.843046,
      "volume": 7421745,
      "time": 1758822088
    },
    "JNJ": {
      "price": 177.0,
      "changePct": 0.17544714,
      "volume": 3595296,
      "time": 1758822085
    },
    "JPM": {
      "price": 313.239,
      "changePct": -0.057749905,
      "volume": 3263638,
      "time": 1758822080
    },
    "MCD": {
      "price": 302.84,
      "changePct": -0.4895969,
      "volume": 1209240,
      "time": 1758822061
    },
    "MRK": {
      "price": 78.165,
      "changePct": -1.8890389,
      "volume": 6451098,
      "time": 1758822087
    },
    "MSFT": {
      "price": 507.64,
      "changePct": -0.4920081,
      "volume": 8114641,
      "time": 1758822087
    },
    "NKE": {
      "price": 69.5,
      "changePct": -2.4150536,
      "volume": 6983292,
      "time": 1758822087
    },
    "NVDA": {
      "price": 177.03,
      "changePct": 0.03390267,
      "volume": 128469933,
      "time": 1758822089
    },
    "PG": {
      "price": 152.4014,
      "changePct": -0.012203427,
      "volume": 3761485,
      "time": 1758822086
    },
    "CRM": {
      "price": 240.145,
      "changePct": -2.3364086,
      "volume": 3981480,
      "time": 1758822084
    },
    "SHW": {
      "price": 340.942,
      "changePct": -0.5884084,
      "volume": 639652,
      "time": 1758822008
    },
    "TRV": {
      "price": 274.92,
      "changePct": -0.6289273,
      "volume": 257897,
      "time": 1758822046
    },
    "UNH": {
      "price": 347.855,
      "changePct": -1.1239691,
      "volume": 5335745,
      "time": 1758822089
    },
    "VZ": {
      "price": 43.3701,
      "changePct": 0.44024503,
      "volume": 9861784,
      "time": 1758822080
    },
    "V": {
      "price": 335.95,
      "changePct": -0.8060649,
      "volume": 2342916,
      "time": 1758822074
    },
    "WMT": {
      "price": 103.345,
      "changePct": 0.59865457,
      "volume": 7136579,
      "time": 1758822090
    },
    "AOS": {
      "price": 71.34,
      "changePct": -0.8615936,
      "volume": 214782,
      "time": 1758822079
    },
    "ABT": {
      "price": 132.47,
      "changePct": -1.0605707,
      "volume": 2116010,
      "time": 1758822087
    },
    "ABBV": {
      "price": 219.02,
      "changePct": -0.44092968,
      "volume": 2319416,
      "time": 1758822087
    },
    "ACN": {
      "price": 233.88,
      "changePct": -2.1750028,
      "volume": 6543658,
      "time": 1758822078
    },
    "ADBE": {
      "price": 353.505,
      "changePct": 0.066525854,
      "volume": 1997170,
      "time": 1758822081
    },
    "AMD": {
      "price": 159.7109,
      "changePct": -0.7266894,
      "volume": 25056722,
      "time": 1758822091
    },
    "AES": {
      "price": 13.04,
      "changePct": -2.3952074,
      "volume": 3940874,
      "time": 1758822076
    },
    "AFL": {
      "price": 108.88,
      "changePct": -0.39337692,
      "volume": 800184,
      "time": 1758822081
    },
    "A": {
      "price": 121.25,
      "changePct": -2.5164795,
      "volume": 576749,
      "time": 1758822065
    },
    "APD": {
      "price": 266.595,
      "changePct": -2.0879233,
      "volume": 819214,
      "time": 1758822080
    },
    "ABNB": {
      "price": 122.03,
      "changePct": -0.85310614,
      "volume": 1571030,
      "time": 1758822092
    },
    "AKAM": {
      "price": 75.28,
      "changePct": -1.2462344,
      "volume": 403360,
      "time": 1758822093
    },
    "ALB": {
      "price": 85.12,
      "changePct": 4.3392997,
      "volume": 3132950,
      "time": 1758822094
    },
    "ARE": {
      "price": 84.18,
      "changePct": -1.9909176,
      "volume": 411512,
      "time": 1758822052
    },
    "ALGN": {
      "price": 124.21,
      "changePct": -3.0972023,
      "volume": 928089,
      "time": 1758822073
    },
    "ALLE": {
      "price": 173.185,
      "changePct": -1.22904,
      "volume": 224565,
      "time": 1758821933
    },
    "LNT": {
      "price": 65.23,
      "changePct": -0.36657685,
      "volume": 790345,
      "time": 1758822046
    },
    "ALL": {
      "price": 209.02,
      "changePct": -0.18623723,
      "volume": 469004,
      "time": 1758822082
    },
    "GOOGL": {
      "price": 244.0601,
      "changePct": -1.2462147,
      "volume": 20432641,
      "time": 1758822094
    },
    "GOOG": {
      "price": 244.96,
      "changePct": -1.15805,
      "volume": 10934279,
      "time": 1758822095
    },
    "MO": {
      "price": 65.09,
      "changePct": -0.06141704,
      "volume": 3149167,
      "time": 1758822094
    },
    "AMCR": {
      "price": 7.995,
      "changePct": 0.18796825,
      "volume": 16795815,
      "time": 1758822096
    },
    "AEE": {
      "price": 100.685,
      "changePct": -0.16361023,
      "volume": 359435,
      "time": 1758822001
    },
    "AEP": {
      "price": 108.4,
      "changePct": -0.44076744,
      "volume": 1043467,
      "time": 1758822095
    },
    "AIG": {
      "price": 77.035,
      "changePct": -1.1101815,
      "volume": 1190451,
      "time": 1758822095
    },
    "AMT": {
      "price": 193.66,
      "changePct": 0.37838128,
      "volume": 1320708,
      "time": 1758822079
    },
    "AWK": {
      "price": 135.795,
      "changePct": -0.45085073,
      "volume": 464654,
      "time": 1758822083
    },
    "AMP": {
      "price": 489.73,
      "changePct": -0.4391233,
      "volume": 161892,
      "time": 1758822013
    },
    "AME": {
      "price": 184.4,
      "changePct": -0.95074624,
      "volume": 461848,
      "time": 1758822063
    },
    "APH": {
      "price": 121.1,
      "changePct": -1.648663,
      "volume": 4348303,
      "time": 1758822096
    },
    "ADI": {
      "price": 247.185,
      "changePct": -0.5731881,
      "volume": 1040737,
      "time": 1758822091
    },
    "ANSS": {
      "price": null,
      "changePct": null,
      "volume": null,
      "time": 1758822106
    },
    "AON": {
      "price": 350.46,
      "changePct": -0.92723435,
      "volume": 570928,
      "time": 1758822080
    },
    "APA": {
      "price": 24.295,
      "changePct": -0.5118755,
      "volume": 4623114,
      "time": 1758822092
    },
    "APO": {
      "price": 136.11,
      "changePct": -0.76553154,
      "volume": 1333048,
      "time": 1758822088
    },
    "AMAT": {
      "price": 199.49,
      "changePct": -0.96802866,
      "volume": 2607623,
      "time": 1758822094
    },
    "APTV": {
      "price": 84.62,
      "changePct": -0.49388307,
      "volume": 891227,
      "time": 1758822090
    },
    "ACGL": {
      "price": 89.3733,
      "changePct": -1.5278795,
      "volume": 966007,
      "time": 1758822087
    },
    "ADM": {
      "price": 61.3051,
      "changePct": -0.28448284,
      "volume": 1336152,
      "time": 1758822082
    },
    "ANET": {
      "price": 141.81,
      "changePct": -0.58188576,
      "volume": 3696566,
      "time": 1758822099
    },
    "AJG": {
      "price": 301.28,
      "changePct": -1.0737118,
      "volume": 610797,
      "time": 1758822004
    },
    "AIZ": {
      "price": 213.35,
      "changePct": -0.8550566,
      "volume": 168268,
      "time": 1758822078
    },
    "T": {
      "price": 28.385,
      "changePct": 0.22952166,
      "volume": 14203257,
      "time": 1758822093
    },
    "ATO": {
      "price": 166.65,
      "changePct": -0.071961604,
      "volume": 239347,
      "time": 1758822046
    },
    "ADSK": {
      "price": 320.4608,
      "changePct": -0.94559973,
      "volume": 453390,
      "time": 1758821733
    },
    "ADP": {
      "price": 288.94,
      "changePct": -0.8782153,
      "volume": 729695,
      "time": 1758822090
    },
    "AZO": {
      "price": 4119.87,
      "changePct": -1.3651304,
      "volume": 54236,
      "time": 1758821618
    },
    "AVB": {
      "price": 192.0,
      "changePct": -0.39944196,
      "volume": 351660,
      "time": 1758822061
    },
    "AVY": {
      "price": 160.3181,
      "changePct": -1.172421,
      "volume": 159257,
      "time": 1758822056
    },
    "AXON": {
      "price": 711.05,
      "changePct": 1.8667041,
      "volume": 615315,
      "time": 1758821987
    },
    "BKR": {
      "price": 49.93,
      "changePct": 0.12031557,
      "volume": 3033017,
      "time": 1758822084
    },
    "BALL": {
      "price": 48.37,
      "changePct": -0.7183955,
      "volume": 1065221,
      "time": 1758822066
    },
    "BAC": {
      "price": 51.855,
      "changePct": 0.2998042,
      "volume": 12861012,
      "time": 1758822101
    },
    "BAX": {
      "price": 21.695,
      "changePct": -3.834219,
      "volume": 3537759,
      "time": 1758822102
    },
    "BDX": {
      "price": 180.505,
      "changePct": -2.9803805,
      "volume": 912985,
      "time": 1758822001
    },
    "BRK.B": {
      "price": null,
      "changePct": null,
      "volume": null,
      "time": 1758822106
    },
    "BBY": {
      "price": 74.3425,
      "changePct": 0.23257464,
      "volume": 1285794,
      "time": 1758822030
    },
    "TECH": {
      "price": 50.275,
      "changePct": -1.8449818,
      "volume": 1302461,
      "time": 1758822087
    },
    "BIIB": {
      "price": 136.5,
      "changePct": -0.84985703,
      "volume": 552065,
      "time": 1758822041
    },
    "BLK": {
      "price": 1137.175,
      "changePct": 0.8151801,
      "volume": 235708,
      "time": 1758822027
    },
    "BX": {
      "price": 175.93,
      "changePct": -1.2073277,
      "volume": 1879203,
      "time": 1758822099
    },
    "BK": {
      "price": 108.21,
      "changePct": 0.09249697,
      "volume": 966101,
      "time": 1758822096
    },
    "BKNG": {
      "price": 5518.91,
      "changePct": -0.12107176,
      "volume": 136118,
      "time": 1758822012
    },
    "BSX": {
      "price": 96.97,
      "changePct": -1.1115606,
      "volume": 4227179,
      "time": 1758822091
    },
    "BMY": {
      "price": 43.305,
      "changePct": -1.9361403,
      "volume": 11876443,
      "time": 1758822103
    },
    "AVGO": {
      "price": 333.71,
      "changePct": -1.6504099,
      "volume": 12467370,
      "time": 1758822099
    },
    "BR": {
      "price": 234.89,
      "changePct": -0.4745541,
      "volume": 273716,
      "time": 1758822000
    },
    "BRO": {
      "price": 92.21,
      "changePct": -1.0834608,
      "volume": 731098,
      "time": 1758822102
    },
    "BF.B": {
      "price": null,
      "changePct": null,
      "volume": null,
      "time": 1561759658
    },
    "BLDR": {
      "price": 117.8625,
      "changePct": -1.1635195,
      "volume": 936929,
      "time": 1758822030
    },
    "BG": {
      "price": 79.29,
      "changePct": 0.37979877,
      "volume": 567058,
      "time": 1758822071
    },
    "BXP": {
      "price": 74.7,
      "changePct": -1.007159,
      "volume": 2819089,
      "time": 1758822095
    },
    "CHRW": {
      "price": 133.31,
      "changePct": 0.0074977544,
      "volume": 723320,
      "time": 1758822092
    },
    "CDNS": {
      "price": 352.21,
      "changePct": -1.3306813,
      "volume": 704050,
      "time": 1758822096
    },
    "CZR": {
      "price": 26.08,
      "changePct": -0.98709273,
      "volume": 2495042,
      "time": 1758822103
    },
    "CPT": {
      "price": 106.12,
      "changePct": -1.0074573,
      "volume": 239081,
      "time": 1758822084
    },
    "CPB": {
      "price": 32.52,
      "changePct": -3.5873084,
      "volume": 1717423,
      "time": 1758822078
    },
    "COF": {
      "price": 221.93,
      "changePct": -1.0742639,
      "volume": 1372652,
      "time": 1758822102
    },
    "CAH": {
      "price": 148.965,
      "changePct": -3.6324267,
      "volume": 1591476,
      "time": 1758822103
    },
    "KMX": {
      "price": 45.47,
      "changePct": -20.29798,
      "volume": 19955667,
      "time": 1758822107
    },
    "CCL": {
      "price": 30.435,
      "changePct": 0.21402247,
      "volume": 11629114,
      "time": 1758822106
    },
    "CARR": {
      "price": 58.553,
      "changePct": -0.74080396,
      "volume": 2197605,
      "time": 1758822090
    },
    "CBOE": {
      "price": 242.85,
      "changePct": -0.13980687,
      "volume": 512710,
      "time": 1758822097
    },
    "CBRE": {
      "price": 156.4,
      "changePct": -0.45824927,
      "volume": 577643,
      "time": 1758821932
    },
    "CDW": {
      "price": 157.44,
      "changePct": -1.8882027,
      "volume": 845784,
      "time": 1758822094
    },
    "COR": {
      "price": 299.12,
      "changePct": -2.9964945,
      "volume": 925634,
      "time": 1758822108
    },
    "CNC": {
      "price": 33.92,
      "changePct": -2.1067917,
      "volume": 6961669,
      "time": 1758822103
    },
    "CNP": {
      "price": 38.319,
      "changePct": -1.7713358,
      "volume": 4176322,
      "time": 1758822100
    },
    "CF": {
      "price": 89.34,
      "changePct": -2.520464,
      "volume": 2488042,
      "time": 1758822019
    },
    "CRL": {
      "price": 145.4,
      "changePct": -2.7099385,
      "volume": 335162,
      "time": 1758822082
    },
    "SCHW": {
      "price": 94.46,
      "changePct": 2.2628803,
      "volume": 5122439,
      "time": 1758822110
    },
    "CHTR": {
      "price": 265.77,
      "changePct": 0.90359324,
      "volume": 751106,
      "time": 1758822016
    },
    "CMG": {
      "price": 39.365,
      "changePct": -0.46775615,
      "volume": 8279300,
      "time": 1758822111
    },
    "CB": {
      "price": 277.79,
      "changePct": -0.16890721,
      "volume": 549265,
      "time": 1758822080
    },
    "CHD": {
      "price": 86.14,
      "changePct": -0.8289215,
      "volume": 744329,
      "time": 1758822063
    },
    "CI": {
      "price": 285.0,
      "changePct": -2.2063594,
      "volume": 630774,
      "time": 1758822104
    },
    "CINF": {
      "price": 154.66,
      "changePct": 0.09066144,
      "volume": 105423,
      "time": 1758822105
    },
    "CTAS": {
      "price": 202.18,
      "changePct": 1.0697857,
      "volume": 912042,
      "time": 1758822087
    },
    "C": {
      "price": 101.755,
      "changePct": 0.103291415,
      "volume": 6850177,
      "time": 1758822112
    },
    "CFG": {
      "price": 52.735,
      "changePct": -0.7808842,
      "volume": 2597823,
      "time": 1758822110
    },
    "CLX": {
      "price": 122.045,
      "changePct": -0.84091944,
      "volume": 869234,
      "time": 1758822074
    },
    "CME": {
      "price": 267.95,
      "changePct": 1.3311726,
      "volume": 1320755,
      "time": 1758822104
    },
    "CMS": {
      "price": 70.16,
      "changePct": -2.0932178,
      "volume": 1525820,
      "time": 1758822109
    },
    "CTSH": {
      "price": 66.94,
      "changePct": -2.0772355,
      "volume": 1627992,
      "time": 1758822093
    },
    "CL": {
      "price": 79.425,
      "changePct": -2.1015582,
      "volume": 3022300,
      "time": 1758822095
    },
    "CMCSA": {
      "price": 31.615,
      "changePct": 0.015815124,
      "volume": 8083973,
      "time": 1758822105
    },
    "CAG": {
      "price": 18.11,
      "changePct": -2.2665951,
      "volume": 5721877,
      "time": 1758822112
    },
    "COP": {
      "price": 96.39,
      "changePct": 0.79489815,
      "volume": 3218953,
      "time": 1758822109
    },
    "ED": {
      "price": 98.35,
      "changePct": -0.465539,
      "volume": 470308,
      "time": 1758822065
    },
    "STZ": {
      "price": 133.015,
      "changePct": -0.28113052,
      "volume": 1383947,
      "time": 1758822110
    },
    "CEG": {
      "price": 329.36,
      "changePct": -2.8809068,
      "volume": 1223241,
      "time": 1758822111
    },
    "COO": {
      "price": 67.27,
      "changePct": -1.5801052,
      "volume": 1546730,
      "time": 1758822095
    },
    "CPRT": {
      "price": 44.98,
      "changePct": -0.8617814,
      "volume": 2700476,
      "time": 1758822113
    },
    "GLW": {
      "price": 78.83,
      "changePct": -1.3515227,
      "volume": 4224110,
      "time": 1758822113
    },
    "CPAY": {
      "price": 290.53,
      "changePct": -1.9241837,
      "volume": 95569,
      "time": 1758821638
    },
    "CTVA": {
      "price": 66.99,
      "changePct": -3.763831,
      "volume": 3515481,
      "time": 1758822084
    },
    "CSGP": {
      "price": 83.36,
      "changePct": -0.8209428,
      "volume": 1134135,
      "time": 1758822112
    },
    "COST": {
      "price": 939.91,
      "changePct": -0.56703866,
      "volume": 1539572,
      "time": 1758822099
    },
    "CTRA": {
      "price": 23.81,
      "changePct": 0.25262934,
      "volume": 2345678,
      "time": 1758822110
    },
    "CRWD": {
      "price": 472.31,
      "changePct": -0.84395045,
      "volume": 1596855,
      "time": 1758822102
    },
    "CCI": {
      "price": 93.965,
      "changePct": 0.27211317,
      "volume": 1033979,
      "time": 1758822099
    },
    "CSX": {
      "price": 33.925,
      "changePct": 0.31046584,
      "volume": 11710724,
      "time": 1758822084
    },
    "CMI": {
      "price": 414.13,
      "changePct": -0.9210981,
      "volume": 450228,
      "time": 1758821956
    },
    "CVS": {
      "price": 74.6,
      "changePct": -2.3304515,
      "volume": 2802222,
      "time": 1758822118
    },
    "DHR": {
      "price": 181.61,
      "changePct": -2.3130732,
      "volume": 3455263,
      "time": 1758822118
    },
    "DRI": {
      "price": 184.89,
      "changePct": -0.921709,
      "volume": 622713,
      "time": 1758822085
    },
    "DVA": {
      "price": 130.37,
      "changePct": -2.4322708,
      "volume": 222227,
      "time": 1758821915
    },
    "DAY": {
      "price": 68.855,
      "changePct": 0.03632359,
      "volume": 794798,
      "time": 1758822116
    },
    "DECK": {
      "price": 106.85,
      "changePct": -3.9377909,
      "volume": 1379253,
      "time": 1758822118
    },
    "DE": {
      "price": 466.15,
      "changePct": -0.5949607,
      "volume": 535292,
      "time": 1758822110
    },
    "DELL": {
      "price": 130.61,
      "changePct": -1.120445,
      "volume": 2655381,
      "time": 1758822111
    },
    "DAL": {
      "price": 56.85,
      "changePct": -1.4902108,
      "volume": 3460213,
      "time": 1758822118
    },
    "DVN": {
      "price": 35.6156,
      "changePct": 1.152133,
      "volume": 2849332,
      "time": 1758822119
    },
    "DXCM": {
      "price": 67.79,
      "changePct": 0.429631,
      "volume": 3766519,
      "time": 1758822120
    },
    "FANG": {
      "price": 145.5798,
      "changePct": 0.6706333,
      "volume": 574223,
      "time": 1758822102
    },
    "DLR": {
      "price": 172.095,
      "changePct": 0.055233266,
      "volume": 456078,
      "time": 1758822096
    },
    "DFS": {
      "price": null,
      "changePct": null,
      "volume": null,
      "time": 1758822128
    },
    "DG": {
      "price": 102.85,
      "changePct": -1.5789489,
      "volume": 911497,
      "time": 1758822117
    },
    "DLTR": {
      "price": 94.145,
      "changePct": -1.8300364,
      "volume": 1435536,
      "time": 1758822118
    },
    "D": {
      "price": 59.785,
      "changePct": -2.0239275,
      "volume": 1514144,
      "time": 1758822109
    },
    "DPZ": {
      "price": 421.67,
      "changePct": -0.8535092,
      "volume": 207674,
      "time": 1758822057
    },
    "DASH": {
      "price": 261.64,
      "changePct": 0.3451808,
      "volume": 1023449,
      "time": 1758822084
    },
    "DOV": {
      "price": 164.445,
      "changePct": -1.7006313,
      "volume": 671885,
      "time": 1758822074
    },
    "DOW": {
      "price": 22.47,
      "changePct": -2.8540535,
      "volume": 9507001,
      "time": 1758822122
    },
    "DHI": {
      "price": 165.76,
      "changePct": -1.0092579,
      "volume": 1127842,
      "time": 1758822116
    },
    "DTE": {
      "price": 137.725,
      "changePct": -0.7458839,
      "volume": 262047,
      "time": 1758822051
    },
    "DUK": {
      "price": 122.58,
      "changePct": -0.85732573,
      "volume": 897782,
      "time": 1758822104
    },
    "DD": {
      "price": 74.8659,
      "changePct": -1.2453495,
      "volume": 832189,
      "time": 1758822112
    },
    "EMN": {
      "price": 62.145,
      "changePct": -2.6400335,
      "volume": 567699,
      "time": 1758822122
    },
    "ETN": {
      "price": 364.12,
      "changePct": -2.1745548,
      "volume": 1157010,
      "time": 1758822120
    },
    "EBAY": {
      "price": 93.13,
      "changePct": -0.24636178,
      "volume": 2852362,
      "time": 1758822122
    },
    "ECL": {
      "price": 268.38,
      "changePct": 0.5168364,
      "volume": 620251,
      "time": 1758822122
    },
    "EIX": {
      "price": 54.12,
      "changePct": -1.6715152,
      "volume": 913984,
      "time": 1758822105
    },
    "EW": {
      "price": 75.18,
      "changePct": 0.69648623,
      "volume": 3118998,
      "time": 1758822123
    },
    "EA": {
      "price": 168.245,
      "changePct": 0.5348007,
      "volume": 846798,
      "time": 1758822074
    },
    "ELV": {
      "price": 316.45,
      "changePct": -3.0424635,
      "volume": 845035,
      "time": 1758822119
    },
    "EMR": {
      "price": 129.92,
      "changePct": -1.5160704,
      "volume": 802626,
      "time": 1758822087
    },
    "ENPH": {
      "price": 36.61,
      "changePct": -3.6325376,
      "volume": 3343988,
      "time": 1758822118
    },
    "ETR": {
      "price": 90.62,
      "changePct": -1.0590606,
      "volume": 1048679,
      "time": 1758822091
    },
    "EOG": {
      "price": 117.04,
      "changePct": 0.2914611,
      "volume": 1594763,
      "time": 1758822124
    },
    "EPAM": {
      "price": 151.095,
      "changePct": -3.4104657,
      "volume": 407142,
      "time": 1758822078
    },
    "EQT": {
      "price": 53.875,
      "changePct": 1.4977357,
      "volume": 7171366,
      "time": 1758822122
    },
    "EFX": {
      "price": 251.9,
      "changePct": -2.1481564,
      "volume": 499231,
      "time": 1758822031
    },
    "EQIX": {
      "price": 787.16,
      "changePct": -0.33300054,
      "volume": 106656,
      "time": 1758822005
    },
    "EQR": {
      "price": 63.81,
      "changePct": -1.0198897,
      "volume": 959292,
      "time": 1758822121
    },
    "ERIE": {
      "price": 310.95,
      "changePct": -1.0564091,
      "volume": 43122,
      "time": 1758822077
    },
    "ESS": {
      "price": 264.1275,
      "changePct": -0.17479645,
      "volume": 94520,
      "time": 1758822084
    },
    "EL": {
      "price": 84.255,
      "changePct": -1.2598202,
      "volume": 1208549,
      "time": 1758822122
    },
    "EG": {
      "price": 343.75,
      "changePct": -0.5180322,
      "volume": 178507,
      "time": 1758822080
    },
    "EVRG": {
      "price": 74.17,
      "changePct": 0.62406605,
      "volume": 1171067,
      "time": 1758822126
    },
    "ES": {
      "price": 68.69,
      "changePct": -0.59333724,
      "volume": 1149273,
      "time": 1758822085
    },
    "EXC": {
      "price": 43.905,
      "changePct": -0.72806746,
      "volume": 1537055,
      "time": 1758822125
    },
    "EXE": {
      "price": 104.365,
      "changePct": 1.2269635,
      "volume": 1768393,
      "time": 1758822125
    },
    "EXPE": {
      "price": 213.72,
      "changePct": -1.8867927,
      "volume": 636953,
      "time": 1758822122
    },
    "EXPD": {
      "price": 121.015,
      "changePct": 0.02893669,
      "volume": 282479,
      "time": 1758822124
    },
    "EXR": {
      "price": 138.04,
      "changePct": 0.2760349,
      "volume": 238590,
      "time": 1758822001
    },
    "XOM": {
      "price": 115.79,
      "changePct": 1.0736761,
      "volume": 5412684,
      "time": 1758822128
    },
    "FFIV": {
      "price": 321.93,
      "changePct": -0.78281766,
      "volume": 112486,
      "time": 1758822005
    },
    "FDS": {
      "price": 283.17,
      "changePct": -1.0448666,
      "volume": 262558,
      "time": 1758822121
    },
    "FICO": {
      "price": 1541.5,
      "changePct": -0.10886958,
      "volume": 81394,
      "time": 1758821895
    },
    "FAST": {
      "price": 47.73,
      "changePct": 0.39970258,
      "volume": 1615082,
      "time": 1758822125
    },
    "FRT": {
      "price": 99.29,
      "changePct": 0.16140792,
      "volume": 136233,
      "time": 1758822066
    },
    "FDX": {
      "price": 235.7,
      "changePct": 0.8342233,
      "volume": 742828,
      "time": 1758822026
    },
    "FIS": {
      "price": 63.935,
      "changePct": -0.30408713,
      "volume": 1453348,
      "time": 1758822130
    },
    "FITB": {
      "price": 45.16,
      "changePct": -0.022134872,
      "volume": 1367663,
      "time": 1758822127
    },
    "FSLR": {
      "price": 219.51,
      "changePct": 0.15512905,
      "volume": 1077938,
      "time": 1758822100
    },
    "FE": {
      "price": 43.928,
      "changePct": -0.34482855,
      "volume": 1782088,
      "time": 1758822123
    },
    "FI": {
      "price": 128.83,
      "changePct": -1.3477254,
      "volume": 1510940,
      "time": 1758822121
    },
    "F": {
      "price": 11.5465,
      "changePct": -0.71796995,
      "volume": 43956276,
      "time": 1758822128
    },
    "FTNT": {
      "price": 82.88,
      "changePct": -0.8612455,
      "volume": 2527403,
      "time": 1758822129
    },
    "FTV": {
      "price": 47.5,
      "changePct": -1.3704315,
      "volume": 1619633,
      "time": 1758822122
    },
    "FOXA": {
      "price": 60.81,
      "changePct": 1.0804547,
      "volume": 1261224,
      "time": 1758822132
    },
    "FOX": {
      "price": 54.73,
      "changePct": 0.7918974,
      "volume": 915768,
      "time": 1758822132
    },
    "BEN": {
      "price": 23.425,
      "changePct": -0.65733963,
      "volume": 1069776,
      "time": 1758822119
    },
    "FCX": {
      "price": 35.665,
      "changePct": -5.3225307,
      "volume": 53853311,
      "time": 1758822133
    },
    "GRMN": {
      "price": 235.71,
      "changePct": -0.3087446,
      "volume": 141380,
      "time": 1758822112
    },
    "IT": {
      "price": 260.8275,
      "changePct": -0.7581206,
      "volume": 1150080,
      "time": 1758822076
    },
    "GE": {
      "price": 298.12,
      "changePct": -0.7259383,
      "volume": 2067393,
      "time": 1758822119
    },
    "GEHC": {
      "price": 70.775,
      "changePct": -4.3319616,
      "volume": 3045358,
      "time": 1758822132
    },
    "GEV": {
      "price": 606.812,
      "changePct": -3.522896,
      "volume": 2021725,
      "time": 1758822132
    },
    "GEN": {
      "price": 28.555,
      "changePct": -1.8391194,
      "volume": 1096583,
      "time": 1758822130
    },
    "GNRC": {
      "price": 164.11,
      "changePct": -1.9419216,
      "volume": 732435,
      "time": 1758822085
    },
    "GD": {
      "price": 323.26,
      "changePct": -0.11123706,
      "volume": 420154,
      "time": 1758822126
    },
    "GIS": {
      "price": 49.13,
      "changePct": -3.87408,
      "volume": 3247236,
      "time": 1758822135
    },
    "GM": {
      "price": 60.025,
      "changePct": 0.17523925,
      "volume": 3332101,
      "time": 1758822134
    },
    "GPC": {
      "price": 136.35,
      "changePct": -1.63047,
      "volume": 332831,
      "time": 1758822067
    },
    "GILD": {
      "price": 111.11,
      "changePct": -2.2521312,
      "volume": 2697173,
      "time": 1758822106
    },
    "GPN": {
      "price": 85.9895,
      "changePct": -1.2863032,
      "volume": 514334,
      "time": 1758822019
    },
    "GL": {
      "price": 142.34,
      "changePct": -0.6699279,
      "volume": 141545,
      "time": 1758821905
    },
    "GDDY": {
      "price": 141.95,
      "changePct": -0.92134243,
      "volume": 442372,
      "time": 1758822125
    },
    "HAL": {
      "price": 24.625,
      "changePct": 0.7569536,
      "volume": 7047129,
      "time": 1758822133
    },
    "HIG": {
      "price": 131.385,
      "changePct": -0.35268226,
      "volume": 580804,
      "time": 1758822127
    },
    "HAS": {
      "price": 74.8925,
      "changePct": -0.44862622,
      "volume": 455946,
      "time": 1758822031
    },
    "HCA": {
      "price": 412.825,
      "changePct": -0.9108979,
      "volume": 289016,
      "time": 1758821952
    },
    "DOC": {
      "price": 18.555,
      "changePct": -0.5093797,
      "volume": 2277375,
      "time": 1758822123
    },
    "HSIC": {
      "price": 66.05,
      "changePct": -2.5101469,
      "volume": 509032,
      "time": 1758822134
    },
    "HSY": {
      "price": 186.175,
      "changePct": -2.470007,
      "volume": 432856,
      "time": 1758822127
    },
    "HES": {
      "price": null,
      "changePct": null,
      "volume": null,
      "time": 1758822139
    },
    "HPE": {
      "price": 24.1399,
      "changePct": -1.3086627,
      "volume": 17447993,
      "time": 1758822133
    },
    "HLT": {
      "price": 260.66,
      "changePct": -0.9537598,
      "volume": 1340012,
      "time": 1758822036
    },
    "HOLX": {
      "price": 65.42,
      "changePct": -1.4759086,
      "volume": 551008,
      "time": 1758822063
    },
    "HRL": {
      "price": 24.37,
      "changePct": -1.3759542,
      "volume": 1121848,
      "time": 1758822108
    },
    "HST": {
      "price": 17.365,
      "changePct": -0.028791409,
      "volume": 3744478,
      "time": 1758822136
    },
    "HWM": {
      "price": 189.23,
      "changePct": -0.5204529,
      "volume": 696480,
      "time": 1758822082
    },
    "HPQ": {
      "price": 26.855,
      "changePct": -2.3454561,
      "volume": 4819394,
      "time": 1758822134
    },
    "HUBB": {
      "price": 420.78,
      "changePct": -2.40746,
      "volume": 335736,
      "time": 1758821940
    },
    "HUM": {
      "price": 255.735,
      "changePct": -2.3800437,
      "volume": 724859,
      "time": 1758822125
    },
    "HBAN": {
      "price": 17.3352,
      "changePct": -0.20035395,
      "volume": 16043998,
      "time": 1758822141
    },
    "HII": {
      "price": 274.4,
      "changePct": -1.120686,
      "volume": 238058,
      "time": 1758822140
    },
    "IEX": {
      "price": 158.67,
      "changePct": -0.6822711,
      "volume": 399632,
      "time": 1758822117
    },
    "IDXX": {
      "price": 616.495,
      "changePct": -1.7020885,
      "volume": 134941,
      "time": 1758822101
    },
    "ITW": {
      "price": 257.81,
      "changePct": -0.67421794,
      "volume": 242693,
      "time": 1758821991
    },
    "INCY": {
      "price": 81.55,
      "changePct": -3.1012363,
      "volume": 475192,
      "time": 1758822030
    },
    "IR": {
      "price": 80.33,
      "changePct": -0.71684813,
      "volume": 1528176,
      "time": 1758822133
    },
    "PODD": {
      "price": 318.35,
      "changePct": -2.636326,
      "volume": 397367,
      "time": 1758822060
    },
    "INTC": {
      "price": 33.335,
      "changePct": 6.772333,
      "volume": 199608077,
      "time": 1758822143
    },
    "ICE": {
      "price": 166.34,
      "changePct": -1.0175582,
      "volume": 1266695,
      "time": 1758822127
    },
    "IFF": {
      "price": 60.79,
      "changePct": -2.7982092,
      "volume": 1061141,
      "time": 1758822136
    },
    "IP": {
      "price": 45.41,
      "changePct": -1.8160201,
      "volume": 950430,
      "time": 1758822141
    },
    "IPG": {
      "price": 25.9,
      "changePct": -1.5209111,
      "volume": 1659485,
      "time": 1758822130
    },
    "INTU": {
      "price": 686.65,
      "changePct": -1.1715704,
      "volume": 674071,
      "time": 1758822101
    },
    "ISRG": {
      "price": 438.08,
      "changePct": -1.3311119,
      "volume": 1571835,
      "time": 1758822139
    },
    "IVZ": {
      "price": 22.285,
      "changePct": 0.47339737,
      "volume": 1081937,
      "time": 1758822076
    },
    "INVH": {
      "price": 28.955,
      "changePct": 0.121022984,
      "volume": 1279751,
      "time": 1758822142
    },
    "IQV": {
      "price": 177.15,
      "changePct": -2.2566826,
      "volume": 576537,
      "time": 1758822116
    },
    "IRM": {
      "price": 100.98,
      "changePct": -0.24696235,
      "volume": 410612,
      "time": 1758822067
    },
    "JBHT": {
      "price": 131.81,
      "changePct": -0.79777044,
      "volume": 470815,
      "time": 1758822124
    },
    "JBL": {
      "price": 212.04,
      "changePct": -5.877133,
      "volume": 2082263,
      "time": 1758822142
    },
    "JKHY": {
      "price": 150.3,
      "changePct": -0.7920772,
      "volume": 435609,
      "time": 1758822116
    },
    "J": {
      "price": 146.05,
      "changePct": -0.9561939,
      "volume": 200160,
      "time": 1758821889
    },
    "JCI": {
      "price": 105.43,
      "changePct": -1.041765,
      "volume": 1711386,
      "time": 1758822138
    },
    "JNPR": {
      "price": null,
      "changePct": null,
      "volume": null,
      "time": 1758822150
    },
    "K": {
      "price": 76.89,
      "changePct": -0.09095713,
      "volume": 1894357,
      "time": 1758822142
    },
    "KVUE": {
      "price": 16.4813,
      "changePct": -2.2461462,
      "volume": 22168236,
      "time": 1758822142
    },
    "KDP": {
      "price": 25.875,
      "changePct": -1.4285715,
      "volume": 8434229,
      "time": 1758822144
    },
    "KEY": {
      "price": 18.7748,
      "changePct": 0.025570208,
      "volume": 15090480,
      "time": 1758822144
    },
    "KEYS": {
      "price": 171.385,
      "changePct": -1.7344241,
      "volume": 320436,
      "time": 1758822094
    },
    "KMB": {
      "price": 121.905,
      "changePct": -1.6339881,
      "volume": 1449093,
      "time": 1758822144
    },
    "KIM": {
      "price": 21.58,
      "changePct": -0.2311569,
      "volume": 879815,
      "time": 1758822116
    },
    "KMI": {
      "price": 28.005,
      "changePct": 0.6649873,
      "volume": 7222671,
      "time": 1758822142
    },
    "KKR": {
      "price": 136.7,
      "changePct": -0.8989455,
      "volume": 1939154,
      "time": 1758822146
    },
    "KLAC": {
      "price": 1058.28,
      "changePct": -0.9722378,
      "volume": 290122,
      "time": 1758822052
    },
    "KHC": {
      "price": 25.8324,
      "changePct": -3.3941677,
      "volume": 7253588,
      "time": 1758822144
    },
    "KR": {
      "price": 65.83,
      "changePct": 0.42715296,
      "volume": 2617240,
      "time": 1758822145
    },
    "LHX": {
      "price": 288.255,
      "changePct": 1.4976876,
      "volume": 572564,
      "time": 1758822148
    },
    "LH": {
      "price": 276.342,
      "changePct": -1.0767838,
      "volume": 171829,
      "time": 1758822096
    },
    "LRCX": {
      "price": 127.96,
      "changePct": -0.28055504,
      "volume": 5424603,
      "time": 1758822144
    },
    "LW": {
      "price": 52.65,
      "changePct": -2.082944,
      "volume": 377954,
      "time": 1758822130
    },
    "LVS": {
      "price": 52.58,
      "changePct": -0.7737306,
      "volume": 1137009,
      "time": 1758822113
    },
    "LDOS": {
      "price": 181.565,
      "changePct": -3.113656,
      "volume": 534891,
      "time": 1758822113
    },
    "LEN": {
      "price": 125.11,
      "changePct": -0.46145424,
      "volume": 1407981,
      "time": 1758822143
    },
    "LII": {
      "price": 513.39,
      "changePct": -1.732254,
      "volume": 323245,
      "time": 1758821834
    },
    "LLY": {
      "price": 718.235,
      "changePct": -3.1832569,
      "volume": 2551353,
      "time": 1758822126
    },
    "LIN": {
      "price": 472.81,
      "changePct": -0.2784062,
      "volume": 680414,
      "time": 1758822136
    },
    "LYV": {
      "price": 162.1,
      "changePct": 0.012342221,
      "volume": 1206599,
      "time": 1758822121
    },
    "LKQ": {
      "price": 29.9324,
      "changePct": -1.5053809,
      "volume": 907308,
      "time": 1758822144
    },
    "LMT": {
      "price": 485.33,
      "changePct": -0.18920584,
      "volume": 679874,
      "time": 1758822134
    },
    "L": {
      "price": 98.96,
      "changePct": -0.30223963,
      "volume": 310726,
      "time": 1758822080
    },
    "LOW": {
      "price": 255.8,
      "changePct": -0.5945609,
      "volume": 1279454,
      "time": 1758822147
    },
    "LULU": {
      "price": 173.35,
      "changePct": -3.2753015,
      "volume": 3198011,
      "time": 1758822138
    },
    "LYB": {
      "price": 49.5,
      "changePct": -3.640255,
      "volume": 3220927,
      "time": 1758822144
    },
    "MTB": {
      "price": 198.485,
      "changePct": -0.47884166,
      "volume": 318207,
      "time": 1758822117
    },
    "MPC": {
      "price": 194.985,
      "changePct": 0.97617525,
      "volume": 712406,
      "time": 1758822136
    },
    "MKTX": {
      "price": 178.02,
      "changePct": -0.569699,
      "volume": 280573,
      "time": 1758822139
    },
    "MAR": {
      "price": 260.08,
      "changePct": -0.78561074,
      "volume": 609656,
      "time": 1758822149
    },
    "MMC": {
      "price": 197.9525,
      "changePct": -0.85520595,
      "volume": 943994,
      "time": 1758822152
    },
    "MLM": {
      "price": 608.3775,
      "changePct": 0.25997275,
      "volume": 110185,
      "time": 1758822024
    },
    "MAS": {
      "price": 70.425,
      "changePct": -1.6135775,
      "volume": 848253,
      "time": 1758822147
    },
    "MA": {
      "price": 566.68,
      "changePct": -0.37446684,
      "volume": 1327580,
      "time": 1758822138
    },
    "MTCH": {
      "price": 35.8306,
      "changePct": -0.74625415,
      "volume": 924996,
      "time": 1758822141
    },
    "MKC": {
      "price": 64.68,
      "changePct": -0.7975409,
      "volume": 1814402,
      "time": 1758822146
    },
    "MCK": {
      "price": 737.6181,
      "changePct": -3.0190005,
      "volume": 757064,
      "time": 1758822073
    },
    "MDT": {
      "price": 93.94,
      "changePct": -1.8800871,
      "volume": 3679993,
      "time": 1758822143
    },
    "META": {
      "price": 747.8599,
      "changePct": -1.6827557,
      "volume": 6462888,
      "time": 1758822152
    },
    "MET": {
      "price": 80.09,
      "changePct": -0.6820474,
      "volume": 976926,
      "time": 1758822132
    },
    "MTD": {
      "price": 1208.97,
      "changePct": -2.681548,
      "volume": 75747,
      "time": 1758819769
    },
    "MGM": {
      "price": 34.18,
      "changePct": -1.0709087,
      "volume": 1861427,
      "time": 1758822145
    },
    "MCHP": {
      "price": 64.5601,
      "changePct": -1.9588394,
      "volume": 1864241,
      "time": 1758822155
    },
    "MU": {
      "price": 155.15,
      "changePct": -4.0566525,
      "volume": 20976156,
      "time": 1758822155
    },
    "MAA": {
      "price": 138.43,
      "changePct": -1.4241972,
      "volume": 243187,
      "time": 1758821980
    },
    "MRNA": {
      "price": 24.92,
      "changePct": -3.7065747,
      "volume": 4943425,
      "time": 1758822156
    },
    "MHK": {
      "price": 125.29,
      "changePct": -2.0100107,
      "volume": 181259,
      "time": 1758822133
    },
    "MOH": {
      "price": 186.635,
      "changePct": -2.1367586,
      "volume": 820103,
      "time": 1758822127
    },
    "TAP": {
      "price": 44.565,
      "changePct": -1.6442347,
      "volume": 1345407,
      "time": 1758822146
    },
    "MDLZ": {
      "price": 62.885,
      "changePct": -2.337321,
      "volume": 3626061,
      "time": 1758822156
    },
    "MPWR": {
      "price": 890.49,
      "changePct": -1.9769962,
      "volume": 118890,
      "time": 1758821738
    },
    "MNST": {
      "price": 64.625,
      "changePct": -0.4697371,
      "volume": 1087871,
      "time": 1758822140
    },
    "MCO": {
      "price": 471.345,
      "changePct": -0.727672,
      "volume": 286725,
      "time": 1758821989
    },
    "MS": {
      "price": 158.15,
      "changePct": 0.171009,
      "volume": 2187920,
      "time": 1758822155
    },
    "MOS": {
      "price": 34.885,
      "changePct": -2.9084384,
      "volume": 6321988,
      "time": 1758822154
    },
    "MSI": {
      "price": 456.35,
      "changePct": 0.26805556,
      "volume": 283853,
      "time": 1758822152
    },
    "MSCI": {
      "price": 562.605,
      "changePct": -0.6735289,
      "volume": 184738,
      "time": 1758822087
    },
    "NDAQ": {
      "price": 86.79,
      "changePct": -0.4130816,
      "volume": 1038414,
      "time": 1758822152
    },
    "NTAP": {
      "price": 120.18,
      "changePct": -2.490872,
      "volume": 686841,
      "time": 1758822145
    },
    "NFLX": {
      "price": 1203.77,
      "changePct": -0.014945109,
      "volume": 1255842,
      "time": 1758822158
    },
    "NEM": {
      "price": 83.32,
      "changePct": -0.17970711,
      "volume": 5259400,
      "time": 1758822158
    },
    "NWSA": {
      "price": 30.295,
      "changePct": 0.21501997,
      "volume": 1015576,
      "time": 1758822120
    },
    "NWS": {
      "price": 33.595,
      "changePct": 0.01489078,
      "volume": 387101,
      "time": 1758822120
    },
    "NEE": {
      "price": 74.38,
      "changePct": 0.7449484,
      "volume": 5186842,
      "time": 1758822158
    },
    "NI": {
      "price": 41.895,
      "changePct": -1.1444092,
      "volume": 1329062,
      "time": 1758822120
    },
    "NDSN": {
      "price": 221.52,
      "changePct": -0.71709883,
      "volume": 79759,
      "time": 1758821928
    },
    "NSC": {
      "price": 294.825,
      "changePct": 0.51318944,
      "volume": 810844,
      "time": 1758822161
    },
    "NTRS": {
      "price": 130.635,
      "changePct": 0.86865884,
      "volume": 436459,
      "time": 1758822016
    },
    "NOC": {
      "price": 586.4125,
      "changePct": 0.02427397,
      "volume": 553525,
      "time": 1758822151
    },
    "NCLH": {
      "price": 25.2,
      "changePct": -0.11890123,
      "volume": 4800035,
      "time": 1758822162
    },
    "NRG": {
      "price": 163.6,
      "changePct": -1.195794,
      "volume": 941506,
      "time": 1758822158
    },
    "NUE": {
      "price": 136.07,
      "changePct": -0.24192566,
      "volume": 657796,
      "time": 1758822131
    },
    "NVR": {
      "price": 7955.0,
      "changePct": -1.015723,
      "volume": 4803,
      "time": 1758821072
    },
    "NXPI": {
      "price": 225.61,
      "changePct": -0.9004669,
      "volume": 794847,
      "time": 1758822158
    },
    "ORLY": {
      "price": 104.14,
      "changePct": 0.6475289,
      "volume": 2008151,
      "time": 1758822160
    },
    "OXY": {
      "price": 46.895,
      "changePct": 0.010665532,
      "volume": 3119377,
      "time": 1758822158
    },
    "ODFL": {
      "price": 140.335,
      "changePct": -0.51419616,
      "volume": 663266,
      "time": 1758822163
    },
    "OMC": {
      "price": 75.74,
      "changePct": -1.7257063,
      "volume": 1179375,
      "time": 1758822162
    },
    "ON": {
      "price": 49.83,
      "changePct": -2.179028,
      "volume": 4188288,
      "time": 1758822162
    },
    "OKE": {
      "price": 73.71,
      "changePct": 0.05429743,
      "volume": 1061328,
      "time": 1758822158
    },
    "ORCL": {
      "price": 290.5608,
      "changePct": -5.8027625,
      "volume": 26537472,
      "time": 1758822164
    },
    "OTIS": {
      "price": 88.91,
      "changePct": 0.20286295,
      "volume": 838512,
      "time": 1758822150
    },
    "PCAR": {
      "price": 95.79,
      "changePct": -1.1353065,
      "volume": 969651,
      "time": 1758822162
    },
    "PKG": {
      "price": 213.77,
      "changePct": -0.7198602,
      "volume": 210165,
      "time": 1758821977
    },
    "PLTR": {
      "price": 178.7868,
      "changePct": -0.43060446,
      "volume": 52984046,
      "time": 1758822165
    },
    "PANW": {
      "price": 202.4201,
      "changePct": 0.85705435,
      "volume": 3719354,
      "time": 1758822161
    },
    "PARA": {
      "price": 11.04,
      "changePct": null,
      "volume": 0,
      "time": 1758822172
    },
    "PH": {
      "price": 743.345,
      "changePct": -0.7232009,
      "volume": 134398,
      "time": 1758822151
    },
    "PAYX": {
      "price": 127.135,
      "changePct": -0.8848539,
      "volume": 1253766,
      "time": 1758822163
    },
    "PAYC": {
      "price": 215.01,
      "changePct": -1.1084554,
      "volume": 299708,
      "time": 1758822141
    },
    "PYPL": {
      "price": 66.725,
      "changePct": -1.6725643,
      "volume": 5473556,
      "time": 1758822164
    },
    "PNR": {
      "price": 107.95,
      "changePct": -0.96330553,
      "volume": 207681,
      "time": 1758822095
    },
    "PEP": {
      "price": 140.315,
      "changePct": -1.3048115,
      "volume": 2529208,
      "time": 1758822166
    },
    "PFE": {
      "price": 23.7354,
      "changePct": -1.4720082,
      "volume": 34453851,
      "time": 1758822166
    },
    "PCG": {
      "price": 14.465,
      "changePct": -1.330148,
      "volume": 7656945,
      "time": 1758822163
    },
    "PM": {
      "price": 164.195,
      "changePct": 0.7331333,
      "volume": 1864044,
      "time": 1758822156
    },
    "PSX": {
      "price": 138.9,
      "changePct": 1.6911908,
      "volume": 2718025,
      "time": 1758822156
    },
    "PNW": {
      "price": 86.0,
      "changePct": -1.3082389,
      "volume": 301828,
      "time": 1758822156
    },
    "PNC": {
      "price": 202.715,
      "changePct": -0.66885805,
      "volume": 338263,
      "time": 1758822165
    },
    "POOL": {
      "price": 306.92,
      "changePct": -1.2197798,
      "volume": 163996,
      "time": 1758822023
    },
    "PPG": {
      "price": 104.65,
      "changePct": -0.78688073,
      "volume": 665908,
      "time": 1758822167
    },
    "PPL": {
      "price": 36.275,
      "changePct": -0.61643416,
      "volume": 1191003,
      "time": 1758822162
    },
    "PFG": {
      "price": 81.3,
      "changePct": -0.65981585,
      "volume": 284187,
      "time": 1758822159
    },
    "PGR": {
      "price": 240.4,
      "changePct": 0.16666412,
      "volume": 897838,
      "time": 1758822148
    },
    "PLD": {
      "price": 113.3085,
      "changePct": 0.39745274,
      "volume": 883093,
      "time": 1758822166
    },
    "PRU": {
      "price": 102.59,
      "changePct": -0.706546,
      "volume": 404138,
      "time": 1758822126
    },
    "PEG": {
      "price": 81.0,
      "changePct": -1.699031,
      "volume": 984898,
      "time": 1758822162
    },
    "PTC": {
      "price": 201.705,
      "changePct": -0.93074864,
      "volume": 215895,
      "time": 1758822086
    },
    "PSA": {
      "price": 281.325,
      "changePct": 0.21909471,
      "volume": 193165,
      "time": 1758822063
    },
    "PHM": {
      "price": 129.24,
      "changePct": -1.2681348,
      "volume": 735345,
      "time": 1758822116
    },
    "PWR": {
      "price": 399.1717,
      "changePct": -0.91798925,
      "volume": 495791,
      "time": 1758822142
    },
    "QCOM": {
      "price": 168.845,
      "changePct": -2.7111135,
      "volume": 4428517,
      "time": 1758822170
    },
    "DGX": {
      "price": 185.165,
      "changePct": -0.8858869,
      "volume": 189385,
      "time": 1758822085
    },
    "RL": {
      "price": 303.4,
      "changePct": -2.759532,
      "volume": 277499,
      "time": 1758821838
    },
    "RJF": {
      "price": 171.675,
      "changePct": -0.13669978,
      "volume": 511472,
      "time": 1758822129
    },
    "RTX": {
      "price": 160.08,
      "changePct": -0.805554,
      "volume": 1592805,
      "time": 1758822165
    },
    "O": {
      "price": 59.68,
      "changePct": -0.50016546,
      "volume": 2103981,
      "time": 1758822159
    },
    "REG": {
      "price": 71.34,
      "changePct": -0.05603939,
      "volume": 225156,
      "time": 1758822110
    },
    "REGN": {
      "price": 556.28,
      "changePct": -3.5876377,
      "volume": 702717,
      "time": 1758822110
    },
    "RF": {
      "price": 26.575,
      "changePct": -0.3188263,
      "volume": 6686760,
      "time": 1758822163
    },
    "RSG": {
      "price": 227.14,
      "changePct": -0.11433356,
      "volume": 563432,
      "time": 1758822121
    },
    "RMD": {
      "price": 266.095,
      "changePct": -2.9523327,
      "volume": 460177,
      "time": 1758822173
    },
    "RVTY": {
      "price": 82.82,
      "changePct": -1.9765632,
      "volume": 395635,
      "time": 1758822170
    },
    "ROK": {
      "price": 339.4225,
      "changePct": -0.89276034,
      "volume": 281526,
      "time": 1758822086
    },
    "ROL": {
      "price": 56.5,
      "changePct": 0.69506216,
      "volume": 765397,
      "time": 1758822170
    },
    "ROP": {
      "price": 495.99,
      "changePct": -1.9162321,
      "volume": 412374,
      "time": 1758822083
    },
    "ROST": {
      "price": 148.91,
      "changePct": -0.3479817,
      "volume": 1263328,
      "time": 1758822172
    },
    "RCL": {
      "price": 325.475,
      "changePct": -0.17022748,
      "volume": 658827,
      "time": 1758822117
    },
    "SPGI": {
      "price": 484.19,
      "changePct": -1.3347166,
      "volume": 1026650,
      "time": 1758822108
    },
    "SBAC": {
      "price": 195.765,
      "changePct": 0.27403763,
      "volume": 277464,
      "time": 1758822162
    },
    "SLB": {
      "price": 34.64,
      "changePct": 0.08667662,
      "volume": 4536521,
      "time": 1758822147
    },
    "STX": {
      "price": 217.67,
      "changePct": -2.6955738,
      "volume": 2496051,
      "time": 1758822171
    },
    "SRE": {
      "price": 86.17,
      "changePct": -1.2717698,
      "volume": 1422314,
      "time": 1758822160
    },
    "NOW": {
      "price": 919.115,
      "changePct": -1.527262,
      "volume": 696275,
      "time": 1758822136
    },
    "SPG": {
      "price": 182.7,
      "changePct": -0.2348102,
      "volume": 387607,
      "time": 1758822167
    },
    "SWKS": {
      "price": 78.83,
      "changePct": -2.2687848,
      "volume": 519011,
      "time": 1758822173
    },
    "SJM": {
      "price": 107.87,
      "changePct": -2.2208095,
      "volume": 546419,
      "time": 1758822144
    },
    "SW": {
      "price": 42.74,
      "changePct": -1.1791868,
      "volume": 1723224,
      "time": 1758822151
    },
    "SNA": {
      "price": 336.505,
      "changePct": -0.8734192,
      "volume": 99125,
      "time": 1758821709
    },
    "SOLV": {
      "price": 70.13,
      "changePct": -2.3531084,
      "volume": 606416,
      "time": 1758822141
    },
    "SO": {
      "price": 93.775,
      "changePct": -0.6726005,
      "volume": 2737201,
      "time": 1758822169
    },
    "LUV": {
      "price": 31.855,
      "changePct": -3.6443422,
      "volume": 4187487,
      "time": 1758822176
    },
    "SWK": {
      "price": 73.51,
      "changePct": -2.1035738,
      "volume": 435486,
      "time": 1758822174
    },
    "SBUX": {
      "price": 83.63,
      "changePct": -0.75946295,
      "volume": 4423021,
      "time": 1758822176
    },
    "STT": {
      "price": 113.66,
      "changePct": 0.61969244,
      "volume": 556295,
      "time": 1758822157
    },
    "STLD": {
      "price": 137.3,
      "changePct": 0.681974,
      "volume": 271809,
      "time": 1758822177
    },
    "STE": {
      "price": 241.35,
      "changePct": -1.8862553,
      "volume": 247746,
      "time": 1758822144
    },
    "SYK": {
      "price": 365.59,
      "changePct": -1.5166222,
      "volume": 748363,
      "time": 1758822167
    },
    "SMCI": {
      "price": 45.589,
      "changePct": -1.322511,
      "volume": 13158463,
      "time": 1758822175
    },
    "SYF": {
      "price": 73.96,
      "changePct": -0.89775985,
      "volume": 811499,
      "time": 1758822160
    },
    "SNPS": {
      "price": 481.35,
      "changePct": 2.887963,
      "volume": 2091248,
      "time": 1758822175
    },
    "SYY": {
      "price": 80.74,
      "changePct": -1.3199729,
      "volume": 2105479,
      "time": 1758822131
    },
    "TMUS": {
      "price": 239.55,
      "changePct": 0.4823864,
      "volume": 1780940,
      "time": 1758822179
    },
    "TROW": {
      "price": 103.26,
      "changePct": -0.1836586,
      "volume": 449433,
      "time": 1758822162
    },
    "TTWO": {
      "price": 245.07,
      "changePct": 0.3891579,
      "volume": 502133,
      "time": 1758822169
    },
    "TPR": {
      "price": 106.63,
      "changePct": -5.9865994,
      "volume": 1998033,
      "time": 1758822176
    },
    "TRGP": {
      "price": 171.66,
      "changePct": -0.3077988,
      "volume": 388090,
      "time": 1758822146
    },
    "TGT": {
      "price": 87.15,
      "changePct": -1.3135501,
      "volume": 4319187,
      "time": 1758822174
    },
    "TEL": {
      "price": 213.05,
      "changePct": -1.1644064,
      "volume": 771144,
      "time": 1758822161
    },
    "TDY": {
      "price": 564.218,
      "changePct": 0.052850526,
      "volume": 95554,
      "time": 1758821892
    },
    "TER": {
      "price": 131.885,
      "changePct": -0.9946792,
      "volume": 1070956,
      "time": 1758822170
    },
    "TSLA": {
      "price": 424.6,
      "changePct": -4.1080427,
      "volume": 62335238,
      "time": 1758822182
    },
    "TXN": {
      "price": 181.14,
      "changePct": -1.7865363,
      "volume": 2031992,
      "time": 1758822172
    },
    "TPL": {
      "price": 924.24,
      "changePct": -1.1508021,
      "volume": 37031,
      "time": 1758819237
    },
    "TXT": {
      "price": 82.25,
      "changePct": -0.6162423,
      "volume": 579357,
      "time": 1758822161
    },
    "TMO": {
      "price": 460.1,
      "changePct": -1.6880329,
      "volume": 1627332,
      "time": 1758822167
    },
    "TJX": {
      "price": 140.8,
      "changePct": 0.25633764,
      "volume": 1893684,
      "time": 1758822183
    },
    "TKO": {
      "price": 195.3,
      "changePct": -0.25026315,
      "volume": 428636,
      "time": 1758822046
    },
    "TSCO": {
      "price": 56.585,
      "changePct": -1.3339136,
      "volume": 1508158,
      "time": 1758822173
    },
    "TT": {
      "price": 405.37,
      "changePct": 0.3167608,
      "volume": 542620,
      "time": 1758822187
    },
    "TDG": {
      "price": 1278.67,
      "changePct": -1.6407659,
      "volume": 130809,
      "time": 1758822180
    },
    "TRMB": {
      "price": 79.26,
      "changePct": -0.77615815,
      "volume": 547759,
      "time": 1758822186
    },
    "TFC": {
      "price": 45.63,
      "changePct": -0.5665686,
      "volume": 1913936,
      "time": 1758822181
    },
    "TYL": {
      "price": 518.64,
      "changePct": -0.81279045,
      "volume": 122945,
      "time": 1758822009
    },
    "TSN": {
      "price": 53.99,
      "changePct": -0.863014,
      "volume": 959734,
      "time": 1758822184
    },
    "USB": {
      "price": 48.93,
      "changePct": -0.5083367,
      "volume": 2536766,
      "time": 1758822183
    },
    "UBER": {
      "price": 97.1705,
      "changePct": -0.6233351,
      "volume": 6024854,
      "time": 1758822185
    },
    "UDR": {
      "price": 36.81,
      "changePct": -0.70137125,
      "volume": 911348,
      "time": 1758822135
    },
    "ULTA": {
      "price": 533.41,
      "changePct": -0.41074893,
      "volume": 215763,
      "time": 1758822150
    },
    "UNP": {
      "price": 231.76,
      "changePct": 0.6077418,
      "volume": 2787467,
      "time": 1758822161
    },
    "UAL": {
      "price": 98.95,
      "changePct": -2.4065514,
      "volume": 2312845,
      "time": 1758822186
    },
    "UPS": {
      "price": 82.7,
      "changePct": -1.4302796,
      "volume": 5139706,
      "time": 1758822188
    },
    "URI": {
      "price": 928.0,
      "changePct": -0.8313951,
      "volume": 188615,
      "time": 1758821811
    },
    "UHS": {
      "price": 196.8625,
      "changePct": -1.4208783,
      "volume": 263209,
      "time": 1758822164
    },
    "VLO": {
      "price": 174.5,
      "changePct": 2.1483335,
      "volume": 1738337,
      "time": 1758822125
    },
    "VTR": {
      "price": 68.7,
      "changePct": 0.32125232,
      "volume": 1007138,
      "time": 1758822172
    },
    "VLTO": {
      "price": 104.79,
      "changePct": -0.7952252,
      "volume": 485228,
      "time": 1758822125
    },
    "VRSN": {
      "price": 284.32,
      "changePct": -0.3295248,
      "volume": 157780,
      "time": 1758822116
    },
    "VRSK": {
      "price": 243.97,
      "changePct": 0.41984123,
      "volume": 529395,
      "time": 1758822163
    },
    "VRTX": {
      "price": 378.99,
      "changePct": 0.6292802,
      "volume": 1201045,
      "time": 1758822162
    },
    "VTRS": {
      "price": 9.525,
      "changePct": -1.9052566,
      "volume": 3761712,
      "time": 1758822184
    },
    "VICI": {
      "price": 32.0144,
      "changePct": 0.39009437,
      "volume": 3388864,
      "time": 1758822182
    },
    "VST": {
      "price": 202.095,
      "changePct": 0.0173234,
      "volume": 2230819,
      "time": 1758822189
    },
    "VMC": {
      "price": 293.99,
      "changePct": 0.061307497,
      "volume": 153597,
      "time": 1758822170
    },
    "WRB": {
      "price": 74.55,
      "changePct": -0.34753978,
      "volume": 861463,
      "time": 1758822170
    },
    "GWW": {
      "price": 950.51,
      "changePct": -0.2539515,
      "volume": 125662,
      "time": 1758821613
    },
    "WAB": {
      "price": 193.98,
      "changePct": 0.86838865,
      "volume": 368658,
      "time": 1758822120
    },
    "WBA": {
      "price": 11.98,
      "changePct": null,
      "volume": 451753578,
      "time": 1758822196
    },
    "WBD": {
      "price": 20.005,
      "changePct": 0.93339795,
      "volume": 25614159,
      "time": 1758822188
    },
    "WM": {
      "price": 218.07,
      "changePct": -0.6152542,
      "volume": 834621,
      "time": 1758822186
    },
    "WAT": {
      "price": 288.055,
      "changePct": -1.5701355,
      "volume": 222124,
      "time": 1758821924
    },
    "WEC": {
      "price": 111.11,
      "changePct": -0.8123514,
      "volume": 822766,
      "time": 1758822165
    },
    "WFC": {
      "price": 83.88,
      "changePct": -0.2734554,
      "volume": 3935709,
      "time": 1758822192
    },
    "WELL": {
      "price": 172.07,
      "changePct": 0.6433913,
      "volume": 1026903,
      "time": 1758822181
    },
    "WST": {
      "price": 253.945,
      "changePct": -2.3062994,
      "volume": 340748,
      "time": 1758822136
    },
    "WDC": {
      "price": 106.8898,
      "changePct": -2.552832,
      "volume": 5310098,
      "time": 1758822183
    },
    "WY": {
      "price": 24.2891,
      "changePct": -1.3039412,
      "volume": 1497175,
      "time": 1758822176
    },
    "WSM": {
      "price": 200.91,
      "changePct": 0.25937963,
      "volume": 451033,
      "time": 1758822192
    },
    "WMB": {
      "price": 62.94,
      "changePct": 0.12726378,
      "volume": 3803999,
      "time": 1758822184
    },
    "WTW": {
      "price": 338.34,
      "changePct": -1.5021845,
      "volume": 204902,
      "time": 1758822141
    },
    "WDAY": {
      "price": 241.16,
      "changePct": -0.14491774,
      "volume": 1197350,
      "time": 1758822177
    },
    "WYNN": {
      "price": 124.55,
      "changePct": -1.0879885,
      "volume": 500947,
      "time": 1758822170
    },
    "XEL": {
      "price": 77.58,
      "changePct": -0.44911903,
      "volume": 5254758,
      "time": 1758822194
    },
    "XYL": {
      "price": 141.1758,
      "changePct": -0.20091206,
      "volume": 298561,
      "time": 1758822173
    },
    "YUM": {
      "price": 150.025,
      "changePct": 0.38474202,
      "volume": 508971,
      "time": 1758822192
    },
    "ZBRA": {
      "price": 301.03,
      "changePct": -2.4150712,
      "volume": 166309,
      "time": 1758822122
    },
    "ZBH": {
      "price": 96.5956,
      "changePct": -2.4089785,
      "volume": 451433,
      "time": 1758822192
    },
    "ZTS": {
      "price": 140.01,
      "changePct": -1.1717397,
      "volume": 1348865,
      "time": 1758822178
    },
    "APP": {
      "price": 633.42,
      "changePct": -1.3241526,
      "volume": 4118012,
      "time": 1758822196
    },
    "ARM": {
      "price": 138.76,
      "changePct": -3.8392296,
      "volume": 2718211,
      "time": 1758822193
    },
    "ASML": {
      "price": 947.1,
      "changePct": 0.016893694,
      "volume": 854776,
      "time": 1758822177
    },
    "AZN": {
      "price": 73.275,
      "changePct": -2.7669022,
      "volume": 2789349,
      "time": 1758822198
    },
    "CCEP": {
      "price": 89.545,
      "changePct": -0.23953204,
      "volume": 572606,
      "time": 1758822180
    },
    "DDOG": {
      "price": 135.53,
      "changePct": -0.76152045,
      "volume": 966919,
      "time": 1758822191
    },
    "GFS": {
      "price": 32.66,
      "changePct": -1.4781348,
      "volume": 597050,
      "time": 1758822196
    },
    "MDB": {
      "price": 313.73,
      "changePct": -0.49793112,
      "volume": 632021,
      "time": 1758822092
    },
    "MELI": {
      "price": 2476.16,
      "changePct": -1.3863192,
      "volume": 179871,
      "time": 1758821988
    },
    "MRVL": {
      "price": 82.71,
      "changePct": 3.2713234,
      "volume": 29351305,
      "time": 1758822199
    },
    "MSTR": {
      "price": 297.095,
      "changePct": -8.108315,
      "volume": 11702758,
      "time": 1758822200
    },
    "PDD": {
      "price": 130.92,
      "changePct": -0.0305502,
      "volume": 3004294,
      "time": 1758822191
    },
    "TEAM": {
      "price": 162.81,
      "changePct": -0.6225992,
      "volume": 1069885,
      "time": 1758822128
    },
    "TTD": {
      "price": 46.91,
      "changePct": 0.08534439,
      "volume": 7632495,
      "time": 1758822187
    },
    "ZS": {
      "price": 285.84,
      "changePct": 0.49925563,
      "volume": 462172,
      "time": 1758822167
    }
  }
}