[
  {
    "name": "MMM",
    "value": 86644289100.0,
    "colorValue": 3.281364,
    "corpName": "3M Company",
    "price": 160.995
  },
  {
    "name": "AXP",
    "value": 258836478450.0,
    "colorValue": 2.7376885,
    "corpName": "American Express Company",
    "price": 369.455
  },
  {
    "name": "AMGN",
    "value": 187408660500.0,
    "colorValue": 1.4464496,
    "corpName": "Amgen Inc",
    "price": 348.57
  },
  {
    "name": "AMZN",
    "value": 2494116847200.0,
    "colorValue": 1.6082319,
    "corpName": "Amazon.Com Inc",
    "price": 235.02
  },
  {
    "name": "AAPL",
    "value": 3759358643299.0,
    "colorValue": 1.0521756,
    "corpName": "Apple Inc.",
    "price": 250.2557
  },
  {
    "name": "BA",
    "value": 190205485950.0,
    "colorValue": 1.0896912,
    "corpName": "Boeing Company",
    "price": 252.795
  },
  {
    "name": "CAT",
    "value": 305858502400.0,
    "colorValue": 0.7654409,
    "corpName": "Caterpillar Inc.",
    "price": 650.32
  },
  {
    "name": "CVX",
    "value": 291946780800.0,
    "colorValue": 0.24590875,
    "corpName": "Chevron Corporation",
    "price": 167.14
  },
  {
    "name": "CSCO",
    "value": 295978809400.0,
    "colorValue": 0.82762444,
    "corpName": "Cisco Systems, Inc. Common Stock (DE)",
    "price": 74.315
  },
  {
    "name": "KO",
    "value": 309283320850.0,
    "colorValue": -0.21524619,
    "corpName": "Coca-Cola Company",
    "price": 71.855
  },
  {
    "name": "DIS",
    "value": 204753910980.0,
    "colorValue": 0.06360974,
    "corpName": "The Walt Disney Company",
    "price": 113.262
  },
  {
    "name": "GS",
    "value": 297343302000.0,
    "colorValue": 1.683086,
    "corpName": "Goldman Sachs Group Inc.",
    "price": 969.05
  },
  {
    "name": "HD",
    "value": 381972268650.0,
    "colorValue": -0.08710013,
    "corpName": "Home Depot, Inc.",
    "price": 384.305
  },
  {
    "name": "HON",
    "value": 143529724400.0,
    "colorValue": 1.8980716,
    "corpName": "Honeywell International, Inc.",
    "price": 223.33
  },
  {
    "name": "IBM",
    "value": 275363765900.0,
    "colorValue": -0.19325542,
    "corpName": "International Business Machines Corporation",
    "price": 296.965
  },
  {
    "name": "JNJ",
    "value": 529739251625.0,
    "colorValue": 0.8313839,
    "corpName": "Johnson & Johnson",
    "price": 219.8225
  },
  {
    "name": "JPM",
    "value": 846885991150.0,
    "colorValue": 0.8922582,
    "corpName": "JPMorgan Chase & Co.",
    "price": 304.735
  },
  {
    "name": "MCD",
    "value": 219097447999.99997,
    "colorValue": 0.23225865,
    "corpName": "McDonald's Corporation",
    "price": 306.4
  },
  {
    "name": "MRK",
    "value": 274430468700.00003,
    "colorValue": -1.6380161,
    "corpName": "Merck & Co., Inc.",
    "price": 109.29
  },
  {
    "name": "MSFT",
    "value": 3351741075700.0,
    "colorValue": 1.5412852,
    "corpName": "Microsoft Corp",
    "price": 450.955
  },
  {
    "name": "NKE",
    "value": 77701585500.0,
    "colorValue": 0.83326685,
    "corpName": "Nike, Inc.",
    "price": 65.955
  },
  {
    "name": "NVDA",
    "value": 4506924000000.0,
    "colorValue": 0.83525175,
    "corpName": "Nvidia Corp",
    "price": 184.71
  },
  {
    "name": "PG",
    "value": 350860411000.0,
    "colorValue": 2.4578915,
    "corpName": "Procter & Gamble Company",
    "price": 149.65
  },
  {
    "name": "CRM",
    "value": 217243197400.0,
    "colorValue": 2.184311,
    "corpName": "Salesforce, Inc.",
    "price": 226.42
  },
  {
    "name": "SHW",
    "value": 88820158000.0,
    "colorValue": -0.5276318,
    "corpName": "The Sherwin-Williams Company",
    "price": 354.43
  },
  {
    "name": "TRV",
    "value": 62661332050.0,
    "colorValue": 1.43591,
    "corpName": "The Travelers Companies, Inc.",
    "price": 276.565
  },
  {
    "name": "UNH",
    "value": 323811913550.0,
    "colorValue": 1.7987074,
    "corpName": "UNITEDHEALTH GROUP INCORPORATED (Delaware)",
    "price": 354.005
  },
  {
    "name": "VZ",
    "value": 166942814700.0,
    "colorValue": 0.904575,
    "corpName": "Verizon Communications",
    "price": 39.595
  },
  {
    "name": "V",
    "value": 555010936200.0,
    "colorValue": -0.27668282,
    "corpName": "VISA Inc.",
    "price": 324.38
  },
  {
    "name": "WMT",
    "value": 947385384900.0,
    "colorValue": -0.795909,
    "corpName": "Walmart Inc.",
    "price": 118.41
  }
]